{"provider":"Unspecified","startDate":1496116800000,"endDate":1496116800000,"numberOfMessage":36731,"numberOfErrors":19,"errors":[{"severity":"ERROR","reportedMessage":"Vaccination admin date is after patient death date","hl7LocationList":[{"line":0,"segmentId":"RXA","segmentSequence":1,"fieldPosition":3,"fieldRepetition":1,"componentNumber":1,"subComponentNumber":1,"baseReference":"RXA-3.1.1","fieldLoc":"RXA-3","abbreviated":"RXA[1]-3"}],"hl7ErrorCode":{"identifier":"0","text":"","nameOfCodingSystem":"","alternateIdentifier":"","alternateText":"","nameOfAlternateCodingSystem":""},"applicationErrorCode":{"identifier":"1","text":"Illogical Date error","nameOfCodingSystem":"HL70533","alternateIdentifier":"MQE0253","alternateText":"Vaccination admin date is after patient death date","nameOfAlternateCodingSystem":"L"},"reportedCount":24,"exampleMessage":"MSH|^~\\&|||||20170530103220-0600||VXU^V04^VXU_V04|3SUt-C.01.51.4f|P|2.5.1|\rPID|||3SUt-C.01.51^^^AIRA-TEST^MR||Green^Bennet^Yashodhar^^^^L|Colfax^Melissa|20130522|M||2106-3^White^HL70005|239 Erie Ave^^GR^MI^49519^USA^P||^PRN^PH^^^616^8912503|||||||||2186-5^not Hispanic or Latino^HL70005|||||||20130522|Y|\rPD1|||||||||||02^Reminder/Recall - any method^HL70215|||||A|20170530|20170530|\rNK1|1|Green^Melissa^^^^^L|MTH^Mother^HL70063|239 Erie Ave^^GR^MI^49519^USA^P|^PRN^PH^^^616^8912503|\rORC|RE||G95I468.3^AIRA|||||||I-23432^Burden^Donna^A^^^^^NIST-AA-1||57422^RADON^NICHOLAS^^^^^^NIST-AA-1^L|\rRXA|0|1|20170530||94^MMRV^CVX|0.5|mL^milliliters^UCUM||00^Administered^NIP001||||||S4121RG||MSD^Merck and Co^MVX||||A|\rRXR|SC^^HL70162|RA^^HL70163|\rOBX|1|CE|64994-7^Vaccine funding program eligibility category^LN|1|V01^Not VFC eligible^HL70064||||||F|||20170530|||VXC40^Eligibility captured at the immunization level^CDCPHINVS|\rOBX|2|CE|30956-7^Vaccine Type^LN|2|94^MMRV^CVX||||||F|\rOBX|3|TS|29768-9^Date vaccine information statement published^LN|2|20100521||||||F|\rOBX|4|TS|29769-7^Date vaccine information statement presented^LN|2|20170530||||||F|","mqeCode":"MQE0253","count":24,"diagnosticMessage":"","source":"MQE"},{"severity":"ERROR","reportedMessage":"Patient submitter id is missing","hl7LocationList":[{"line":0,"segmentId":"PID","segmentSequence":1,"fieldPosition":3,"fieldRepetition":1,"componentNumber":1,"subComponentNumber":1,"baseReference":"PID-3.1.1","fieldLoc":"PID-3","abbreviated":"PID-3"}],"hl7ErrorCode":{"identifier":"101","text":"","nameOfCodingSystem":"","alternateIdentifier":"","alternateText":"","nameOfAlternateCodingSystem":""},"applicationErrorCode":{"identifier":"4","text":"Invalid value","nameOfCodingSystem":"HL70533","alternateIdentifier":"MQE0220","alternateText":"Patient submitter id is missing","nameOfAlternateCodingSystem":"L"},"reportedCount":161,"exampleMessage":"MSH|^~\\&|||||20170530103218-0600||VXU^V04^VXU_V04|3SUt-K.01.02.2ck|P|2.5.1|\rPID|||||Lee^Abira^Flo^^^^L|Mahoney^Heidi|20130613|F||2054-5^Black or African-American^HL70005|182 El Dorado Cir^^Bronson^MI^49028^USA^P||^PRN^PH^^^517^3641220|||||||||2135-2^Hispanic or Latino^HL70005|\rPD1|||||||||||02^Reminder/Recall - any method^HL70215|||||A|20170530|20170530|\rNK1|1|Lee^Heidi^^^^^L|MTH^Mother^HL70063|182 El Dorado Cir^^Bronson^MI^49028^USA^P|^PRN^PH^^^517^3641220|\rORC|RE||T53P11.3^AIRA|||||||I-23432^Burden^Donna^A^^^^^NIST-AA-1||57422^RADON^NICHOLAS^^^^^^NIST-AA-1^L|\rRXA|0|1|20170530||21^Varicella^CVX|0.5|mL^milliliters^UCUM||00^Administered^NIP001||||||N3783EO||MSD^Merck and Co^MVX||||A|\rRXR|SC^^HL70162|RA^^HL70163|\rOBX|1|CE|64994-7^Vaccine funding program eligibility category^LN|1|V02^VFC eligible - Medicaid/Medicaid Managed Care^HL70064||||||F|||20170530|||VXC40^Eligibility captured at the immunization level^CDCPHINVS|\rOBX|2|CE|30956-7^Vaccine Type^LN|2|21^Varicella^CVX||||||F|\rOBX|3|TS|29768-9^Date vaccine information statement published^LN|2|20080313||||||F|\rOBX|4|TS|29769-7^Date vaccine information statement presented^LN|2|20170530||||||F|","mqeCode":"MQE0220","count":161,"diagnosticMessage":"","source":"MQE"},{"severity":"ERROR","reportedMessage":"Vaccination admin code is unrecognized","hl7LocationList":[{"line":0,"segmentId":"RXA","segmentSequence":1,"fieldPosition":5,"fieldRepetition":1,"componentNumber":1,"subComponentNumber":1,"baseReference":"RXA-5.1.1","fieldLoc":"RXA-5","abbreviated":"RXA[1]-5"}],"hl7ErrorCode":{"identifier":"103","text":"","nameOfCodingSystem":"","alternateIdentifier":"","alternateText":"","nameOfAlternateCodingSystem":""},"applicationErrorCode":{"identifier":"4","text":"Invalid value","nameOfCodingSystem":"HL70533","alternateIdentifier":"MQE0247","alternateText":"Vaccination admin code is unrecognized","nameOfAlternateCodingSystem":"L"},"reportedCount":32,"exampleMessage":"MSH|^~\\&|||||20170530103220-0600||VXU^V04^VXU_V04|3SUt-C.01.49.47|P|2.5.1|\rPID|||3SUt-C.01.49^^^AIRA-TEST^MR||Berks^Laraine^^^^^L|Canadian^Shubha|20130527|F||2106-3^White^HL70005|106 Miami Pl^^Grand Rapids^MI^49519^USA^P||^PRN^PH^^^616^3801293|||||||||2186-5^not Hispanic or Latino^HL70005|\rPD1|||||||||||02^Reminder/Recall - any method^HL70215|||||A|20170530|20170530|\rNK1|1|Canadian^Shubha^^^^^L|MTH^Mother^HL70063|106 Miami Pl^^Grand Rapids^MI^49519^USA^P|^PRN^PH^^^616^3801293|\rORC|RE||U22W466.3^AIRA|||||||I-23432^Burden^Donna^A^^^^^NIST-AA-1||57422^RADON^NICHOLAS^^^^^^NIST-AA-1^L|\rRXA|0|1|20170530||PCV^MMR^CVX|0.5|mL^milliliters^UCUM||00^Administered^NIP001||||||Z7029FR||MSD^Merck and Co^MVX||||A|\rRXR|SC^^HL70162|LA^^HL70163|\rOBX|1|CE|64994-7^Vaccine funding program eligibility category^LN|1|V02^VFC eligible - Medicaid/Medicaid Managed Care^HL70064||||||F|||20170530|||VXC40^Eligibility captured at the immunization level^CDCPHINVS|\rOBX|2|CE|30956-7^Vaccine Type^LN|2|03^MMR^CVX||||||F|\rOBX|3|TS|29768-9^Date vaccine information statement published^LN|2|20120420||||||F|\rOBX|4|TS|29769-7^Date vaccine information statement presented^LN|2|20170530||||||F|","mqeCode":"MQE0247","count":32,"diagnosticMessage":"","source":"MQE"},{"severity":"ERROR","reportedMessage":"Patient submitter id type code is missing","hl7LocationList":[{"line":0,"segmentId":"PID","segmentSequence":1,"fieldPosition":3,"fieldRepetition":1,"componentNumber":5,"subComponentNumber":1,"baseReference":"PID-3.5.1","fieldLoc":"PID-3","abbreviated":"PID-3.5"}],"hl7ErrorCode":{"identifier":"101","text":"","nameOfCodingSystem":"","alternateIdentifier":"","alternateText":"","nameOfAlternateCodingSystem":""},"applicationErrorCode":{"identifier":"4","text":"Invalid value","nameOfCodingSystem":"HL70533","alternateIdentifier":"MQE0394","alternateText":"Patient submitter id type code is missing","nameOfAlternateCodingSystem":"L"},"reportedCount":145,"exampleMessage":"MSH|^~\\&|||||20170530103218-0600||VXU^V04^VXU_V04|3SUt-K.01.02.2ck|P|2.5.1|\rPID|||||Lee^Abira^Flo^^^^L|Mahoney^Heidi|20130613|F||2054-5^Black or African-American^HL70005|182 El Dorado Cir^^Bronson^MI^49028^USA^P||^PRN^PH^^^517^3641220|||||||||2135-2^Hispanic or Latino^HL70005|\rPD1|||||||||||02^Reminder/Recall - any method^HL70215|||||A|20170530|20170530|\rNK1|1|Lee^Heidi^^^^^L|MTH^Mother^HL70063|182 El Dorado Cir^^Bronson^MI^49028^USA^P|^PRN^PH^^^517^3641220|\rORC|RE||T53P11.3^AIRA|||||||I-23432^Burden^Donna^A^^^^^NIST-AA-1||57422^RADON^NICHOLAS^^^^^^NIST-AA-1^L|\rRXA|0|1|20170530||21^Varicella^CVX|0.5|mL^milliliters^UCUM||00^Administered^NIP001||||||N3783EO||MSD^Merck and Co^MVX||||A|\rRXR|SC^^HL70162|RA^^HL70163|\rOBX|1|CE|64994-7^Vaccine funding program eligibility category^LN|1|V02^VFC eligible - Medicaid/Medicaid Managed Care^HL70064||||||F|||20170530|||VXC40^Eligibility captured at the immunization level^CDCPHINVS|\rOBX|2|CE|30956-7^Vaccine Type^LN|2|21^Varicella^CVX||||||F|\rOBX|3|TS|29768-9^Date vaccine information statement published^LN|2|20080313||||||F|\rOBX|4|TS|29769-7^Date vaccine information statement presented^LN|2|20170530||||||F|","mqeCode":"MQE0394","count":145,"diagnosticMessage":"","source":"MQE"},{"severity":"ERROR","reportedMessage":"Vaccination admin code is missing","hl7LocationList":[{"line":0,"segmentId":"RXA","segmentSequence":1,"fieldPosition":5,"fieldRepetition":1,"componentNumber":1,"subComponentNumber":1,"baseReference":"RXA-5.1.1","fieldLoc":"RXA-5","abbreviated":"RXA[1]-5"}],"hl7ErrorCode":{"identifier":"101","text":"","nameOfCodingSystem":"","alternateIdentifier":"","alternateText":"","nameOfAlternateCodingSystem":""},"applicationErrorCode":{"identifier":"4","text":"Invalid value","nameOfCodingSystem":"HL70533","alternateIdentifier":"MQE0244","alternateText":"Vaccination admin code is missing","nameOfAlternateCodingSystem":"L"},"reportedCount":138,"exampleMessage":"MSH|^~\\&|||||20170530103218-0600||VXU^V04^VXU_V04|3SUt-K.01.11.2dC|P|2.5.1|\rPID|||3SUt-K.01.11^^^AIRA-TEST^MR||Cherokee^Firdos^Vaclav^^^^L|McCracken^Leela|20130530|M||2106-3^White^HL70005|357 Nordholm Cir^^Dodgeville^MI^49921^USA^P||^PRN^PH^^^906^7068235|||||||||2135-2^Hispanic or Latino^HL70005|\rPD1|||||||||||02^Reminder/Recall - any method^HL70215|||||A|20170530|20170530|\rNK1|1|Cherokee^Leela^^^^^L|MTH^Mother^HL70063|357 Nordholm Cir^^Dodgeville^MI^49921^USA^P|^PRN^PH^^^906^7068235|\rORC|RE||C46V20.3^AIRA|||||||I-23432^Burden^Donna^A^^^^^NIST-AA-1||57422^RADON^NICHOLAS^^^^^^NIST-AA-1^L|\rRXA|0|1|20170530||^MMR^CVX|0.5|mL^milliliters^UCUM||00^Administered^NIP001||||||V7634SH||MSD^Merck and Co^MVX||||A|\rRXR|SC^^HL70162|LA^^HL70163|\rOBX|1|CE|64994-7^Vaccine funding program eligibility category^LN|1|V05^VFC eligible - Federally Qualified Health Center Patient (under-insured)^HL70064||||||F|||20170530|||VXC40^Eligibility captured at the immunization level^CDCPHINVS|\rOBX|2|CE|30956-7^Vaccine Type^LN|2|03^MMR^CVX||||||F|\rOBX|3|TS|29768-9^Date vaccine information statement published^LN|2|20120420||||||F|\rOBX|4|TS|29769-7^Date vaccine information statement presented^LN|2|20170530||||||F|","mqeCode":"MQE0244","count":138,"diagnosticMessage":"","source":"MQE"},{"severity":"ERROR","reportedMessage":"Patient birth date is invalid","hl7LocationList":[{"line":0,"segmentId":"PID","segmentSequence":1,"fieldPosition":7,"fieldRepetition":1,"componentNumber":1,"subComponentNumber":1,"baseReference":"PID-7.1.1","fieldLoc":"PID-7","abbreviated":"PID-7"}],"hl7ErrorCode":{"identifier":"102","text":"","nameOfCodingSystem":"","alternateIdentifier":"","alternateText":"","nameOfAlternateCodingSystem":""},"applicationErrorCode":{"identifier":"4","text":"Invalid value","nameOfCodingSystem":"HL70533","alternateIdentifier":"MQE0117","alternateText":"Patient birth date is invalid","nameOfAlternateCodingSystem":"L"},"reportedCount":64,"exampleMessage":"MSH|^~\\&|||||20170530103230-0600||VXU^V04^VXU_V04|3SUt-I.01.19822.aV|P|2.5.1|||NE|AL||||||Piscataquis Pediatrics|\rPID|||3SUt-I.01.19822^^^AIRA-TEST^MR||Harlan^Searlait^Mamta^^^^L|Thompsen^Dominique|2013|F||2054-5^Black or African-American^HL70005|112 Holmf Cir^APT #350^Harvey^MI^49855^USA^P||^PRN^PH^^^906^4670548~^NET^X.400^dominique.harlan@madeupemailaddress.com|^WPN^PH^^^906^4670548|eng^English^HL70296|||||||2135-2^Hispanic or Latino^HL70005||N|1|||||N|\rPD1|||||||||||02^Reminder/recall - any method^HL70215|N|20170530|||A|20170530|20170530|\rNK1|1|Harlan^Dominique^Mamta^^^^L|MTH^Mother^HL70063|112 Holmf Cir^APT #350^Harvey^MI^49855^USA^P|^PRN^PH^^^906^4670548|^WPN^PH^^^906^4670548|\rPV1|1|R|\rORC|RE||U77O1036.1^AIRA|||||||2099117201^Aslsen^Zenobio^Vavrin^^^^^CNS^L^^^NPI||8077427876^Klamath^Avram^Renny^^^^^CMS^L^^^NPI|||||^Piscataquis Pediatrics - Ottawa^HL70362|\rRXA|0|1|20140605|20140605|21^Varicella^CVX|0.5|mL^milliliters^UCUM||00^Administered^NIP001|3203300875^Breathitt^Jared^Aron^^^^^CMS^L^^^NPI|||||Y5841RR|20180530|MSD^Merck and Co^MVX|||CP|A|20170530103230-0600|\rRXR|SC^^HL70162|RA^^HL70163|\rOBX|1|CE|64994-7^Vaccine funding program eligibility category^LN|1|V03^VFC eligible - Uninsured^HL70064||||||F|||20170530|||VXC40^Eligibility captured at the immunization level^CDCPHINVS|\rOBX|2|CE|30956-7^Vaccine Type^LN|2|21^Varicella^CVX||||||F|\rOBX|3|TS|29768-9^Date vaccine information statement published^LN|2|20080313||||||F|\rOBX|4|TS|29769-7^Date vaccine information statement presented^LN|2|20140605||||||F|\rORC|RE||U77O1036.2^AIRA|\rRXA|0|1|20141229|20141229|21^Varicella^CVX|999|||01^Historical^NIP001|||||||||||CP|A|\rORC|RE||U77O1036.3^AIRA|||||||2099117201^Aslsen^Zenobio^Vavrin^^^^^CMS^L^^^NPI||8077427876^Klamath^Avram^Renny^^^^^CMS^L^^^NPI|||||^Piscataquis Pediatrics - Ottawa^HL70362|\rRXA|0|1|20170530||21^Varicella^CVX|0.5|mL^milliliters^UCUM||00^Administered^NIP001||||||G3407KC|20180530|MSD^Merck and Co^MVX|||CP|A|\rRXR|SC^^HL70162|LA^^HL70163|\rOBX|1|CE|64994-7^Vaccine funding program eligibility category^LN|1|V03^VFC eligible - Uninsured^HL70064||||||F|||20170530|||VXC40^Eligibility captured at the immunization level^CDCPHINVS|\rOBX|2|CE|30956-7^Vaccine Type^LN|2|21^Varicella^CVX||||||F|\rOBX|3|TS|29768-9^Date vaccine information statement published^LN|2|20080313||||||F|\rOBX|4|TS|29769-7^Date vaccine information statement presented^LN|2|20170530||||||F|","mqeCode":"MQE0117","count":64,"diagnosticMessage":"","source":"MQE"},{"severity":"ERROR","reportedMessage":"Vaccination action code is missing","hl7LocationList":[{"line":0,"segmentId":"RXA","segmentSequence":1,"fieldPosition":21,"fieldRepetition":1,"componentNumber":1,"subComponentNumber":1,"baseReference":"RXA-21.1.1","fieldLoc":"RXA-21","abbreviated":"RXA[1]-21"}],"hl7ErrorCode":{"identifier":"101","text":"","nameOfCodingSystem":"","alternateIdentifier":"","alternateText":"","nameOfAlternateCodingSystem":""},"applicationErrorCode":{"identifier":"4","text":"Invalid value","nameOfCodingSystem":"HL70533","alternateIdentifier":"MQE0235","alternateText":"Vaccination action code is missing","nameOfAlternateCodingSystem":"L"},"reportedCount":54757,"exampleMessage":"MSH|^~\\&|||||20170530103254-0600||VXU^V04^VXU_V04|3SUt-F.116.14093.14H|P|2.5.1|\rPID|||SUt-F.116.14093^^^AIRA-TEST^MR||Brikke^Kaede^Buffy^^^^L|Johnson^Avanti|20090809|F||2106-3^White^CDCREC|370 Wrigley Ave^^Luna Pier^MI^48157^USA^P||^PRN^PH^^^734^7785249|||||||||2186-5^not Hispanic or Latino^CDCREC|\rNK1|1|Sherman^Avanti^^^^^L|MTH^Mother^HL70063|370 Wrigley Ave^^Luna Pier^MI^48157^USA^P|^PRN^PH^^^734^7785249|\rORC|RE||111382^TCH-FT|\rRXA|0|1|20091009||110^DTaP-Hep B-IPV^CVX|999|||01^Historical^NIP001|\rORC|RE||111383^TCH-FT|\rRXA|0|1|20091209||110^DTaP-Hep B-IPV^CVX|999|||01^Historical^NIP001|\rORC|RE||111384^TCH-FT|\rRXA|0|1|20100409||110^DTaP-Hep B-IPV^CVX|999|||01^Historical^NIP001|\rORC|RE||111385^TCH-FT|\rRXA|0|1|20101005||110^DTaP-Hep B-IPV^CVX|999|||01^Historical^NIP001|","mqeCode":"MQE0235","count":54757,"diagnosticMessage":"","source":"MQE"},{"severity":"ERROR","reportedMessage":"Vaccination admin date is before birth","hl7LocationList":[{"line":0,"segmentId":"RXA","segmentSequence":1,"fieldPosition":3,"fieldRepetition":1,"componentNumber":1,"subComponentNumber":1,"baseReference":"RXA-3.1.1","fieldLoc":"RXA-3","abbreviated":"RXA[1]-3"}],"hl7ErrorCode":{"identifier":"0","text":"","nameOfCodingSystem":"","alternateIdentifier":"","alternateText":"","nameOfAlternateCodingSystem":""},"applicationErrorCode":{"identifier":"1","text":"Illogical Date error","nameOfCodingSystem":"HL70533","alternateIdentifier":"MQE0255","alternateText":"Vaccination admin date is before birth","nameOfAlternateCodingSystem":"L"},"reportedCount":56,"exampleMessage":"MSH|^~\\&|||||20170530103220-0600||VXU^V04^VXU_V04|3SUt-C.01.21.3b|P|2.5.1|\rPID|||3SUt-C.01.21^^^AIRA-TEST^MR||Harney^Olono^Rini^^^^L|Thurston^Sashenka|20180530|F||2106-3^White^HL70005|244 Simpson Pl^^Sodus^MI^49126^USA^P||^PRN^PH^^^269^9486443|||||||||2135-2^Hispanic or Latino^HL70005|\rPD1|||||||||||02^Reminder/Recall - any method^HL70215|||||A|20170530|20170530|\rNK1|1|Harney^Sashenka^^^^^L|MTH^Mother^HL70063|244 Simpson Pl^^Sodus^MI^49126^USA^P|^PRN^PH^^^269^9486443|\rORC|RE||S63I438.3^AIRA|||||||I-23432^Burden^Donna^A^^^^^NIST-AA-1||57422^RADON^NICHOLAS^^^^^^NIST-AA-1^L|\rRXA|0|1|20170530||03^MMR^CVX|0.5|mL^milliliters^UCUM||00^Administered^NIP001||||||Z7029FR||MSD^Merck and Co^MVX||||A|\rRXR|SC^^HL70162|LA^^HL70163|\rOBX|1|CE|64994-7^Vaccine funding program eligibility category^LN|1|V02^VFC eligible - Medicaid/Medicaid Managed Care^HL70064||||||F|||20170530|||VXC40^Eligibility captured at the immunization level^CDCPHINVS|\rOBX|2|CE|30956-7^Vaccine Type^LN|2|03^MMR^CVX||||||F|\rOBX|3|TS|29768-9^Date vaccine information statement published^LN|2|20120420||||||F|\rOBX|4|TS|29769-7^Date vaccine information statement presented^LN|2|20170530||||||F|","mqeCode":"MQE0255","count":56,"diagnosticMessage":"","source":"MQE"},{"severity":"ERROR","reportedMessage":"Patient name first is invalid","hl7LocationList":[{"line":0,"segmentId":"PID","segmentSequence":1,"fieldPosition":5,"fieldRepetition":1,"componentNumber":2,"subComponentNumber":1,"baseReference":"PID-5.2.1","fieldLoc":"PID-5","abbreviated":"PID-5.2"}],"hl7ErrorCode":{"identifier":"102","text":"","nameOfCodingSystem":"","alternateIdentifier":"","alternateText":"","nameOfAlternateCodingSystem":""},"applicationErrorCode":{"identifier":"4","text":"Invalid value","nameOfCodingSystem":"HL70533","alternateIdentifier":"MQE0140","alternateText":"Patient name first is invalid","nameOfAlternateCodingSystem":"L"},"reportedCount":12,"exampleMessage":"MSH|^~\\&|||||20170530103220-0600||VXU^V04^VXU_V04|3SUt-C.01.35.3C|P|2.5.1|\rPID|||3SUt-C.01.35^^^AIRA-TEST^MR||Cannavin^Apt #5^^^^^L|Figgens^Jaida|20130529|F||1002-5^American Indian or Alaska Native^HL70005|58 Washington Ave^^Merriweather^MI^49947^USA^P||^PRN^PH^^^906^2069558|||||||||2135-2^Hispanic or Latino^HL70005|\rPD1|||||||||||02^Reminder/Recall - any method^HL70215|||||A|20170530|20170530|\rNK1|1|Cannavin^Jaida^^^^^L|MTH^Mother^HL70063|58 Washington Ave^^Merriweather^MI^49947^USA^P|^PRN^PH^^^906^2069558|\rORC|RE||V21Y452.3^AIRA|||||||I-23432^Burden^Donna^A^^^^^NIST-AA-1||57422^RADON^NICHOLAS^^^^^^NIST-AA-1^L|\rRXA|0|1|20170530||94^MMRV^CVX|0.5|mL^milliliters^UCUM||00^Administered^NIP001||||||L6696AE||MSD^Merck and Co^MVX||||A|\rRXR|SC^^HL70162|RA^^HL70163|\rOBX|1|CE|64994-7^Vaccine funding program eligibility category^LN|1|V02^VFC eligible - Medicaid/Medicaid Managed Care^HL70064||||||F|||20170530|||VXC40^Eligibility captured at the immunization level^CDCPHINVS|\rOBX|2|CE|30956-7^Vaccine Type^LN|2|94^MMRV^CVX||||||F|\rOBX|3|TS|29768-9^Date vaccine information statement published^LN|2|20100521||||||F|\rOBX|4|TS|29769-7^Date vaccine information statement presented^LN|2|20170530||||||F|","mqeCode":"MQE0140","count":12,"diagnosticMessage":"","source":"MQE"},{"severity":"ERROR","reportedMessage":"Vaccination admin date is invalid","hl7LocationList":[{"line":0,"segmentId":"RXA","segmentSequence":1,"fieldPosition":3,"fieldRepetition":1,"componentNumber":1,"subComponentNumber":1,"baseReference":"RXA-3.1.1","fieldLoc":"RXA-3","abbreviated":"RXA[1]-3"}],"hl7ErrorCode":{"identifier":"102","text":"","nameOfCodingSystem":"","alternateIdentifier":"","alternateText":"","nameOfAlternateCodingSystem":""},"applicationErrorCode":{"identifier":"4","text":"Invalid value","nameOfCodingSystem":"HL70533","alternateIdentifier":"MQE0260","alternateText":"Vaccination admin date is invalid","nameOfAlternateCodingSystem":"L"},"reportedCount":48,"exampleMessage":"MSH|^~\\&|||||20170530103231-0600||VXU^V04^VXU_V04|3SUt-I.01.26638.hX|P|2.5.1|||NE|AL||||||Muscatine Pediatrics|\rPID|||3SUt-I.01.26638^^^AIRA-TEST^MR||Butler^Basil^Knox^^^^L|Greenlee^Edith|20130525|M||2106-3^White^HL70005|311 Cass Pl^APT #90^Kincheloe^MI^49784^USA^P||^PRN^PH^^^906^6869447~^NET^X.400^edith.butler@madeupemailaddress.com|^WPN^PH^^^906^6869447|eng^English^HL70296|||||||2135-2^Hispanic or Latino^HL70005||N|1|||||N|\rPD1|||||||||||02^Reminder/recall - any method^HL70215|N|20170530|||A|20170530|20170530|\rNK1|1|Butler^Edith^Manuella^^^^L|MTH^Mother^HL70063|311 Cass Pl^APT #90^Kincheloe^MI^49784^USA^P|^PRN^PH^^^906^6869447|^WPN^PH^^^906^6869447|\rPV1|1|R|\rORC|RE||Q25B1080.1^AIRA|||||||8068062301^Tobin^Ryman^Drake^^^^^CNS^L^^^NPI||0201583728^Monona^Oola^Jendayi^^^^^CMS^L^^^NPI|||||^Muscatine Pediatrics - Jensen^HL70362|\rRXA|0|1|201405|20140527|21^Varicella^CVX|0.5|mL^milliliters^UCUM||00^Administered^NIP001|5851564417^Sanilac^Damara^Jenay^^^^^CMS^L^^^NPI|||||N3783EO|20180530|MSD^Merck and Co^MVX|||CP|A|20170530103231-0600|\rRXR|SC^^HL70162|RA^^HL70163|\rOBX|1|CE|64994-7^Vaccine funding program eligibility category^LN|1|V04^VFC eligible - American Indian/Alaskan Native^HL70064||||||F|||20170530|||VXC40^Eligibility captured at the immunization level^CDCPHINVS|\rOBX|2|CE|30956-7^Vaccine Type^LN|2|21^Varicella^CVX||||||F|\rOBX|3|TS|29768-9^Date vaccine information statement published^LN|2|20080313||||||F|\rOBX|4|TS|29769-7^Date vaccine information statement presented^LN|2|20140527||||||F|\rORC|RE||Q25B1080.2^AIRA|\rRXA|0|1|20141225|20141225|94^MMRV^CVX|999|||01^Historical^NIP001|||||||||||CP|A|\rORC|RE||Q25B1080.3^AIRA|||||||8068062301^Tobin^Ryman^Drake^^^^^CMS^L^^^NPI||0201583728^Monona^Oola^Jendayi^^^^^CMS^L^^^NPI|||||^Muscatine Pediatrics - Jensen^HL70362|\rRXA|0|1|20170530||21^Varicella^CVX|0.5|mL^milliliters^UCUM||00^Administered^NIP001||||||Y5841RR|20180530|MSD^Merck and Co^MVX|||CP|A|\rRXR|SC^^HL70162|RA^^HL70163|\rOBX|1|CE|64994-7^Vaccine funding program eligibility category^LN|1|V04^VFC eligible - American Indian/Alaskan Native^HL70064||||||F|||20170530|||VXC40^Eligibility captured at the immunization level^CDCPHINVS|\rOBX|2|CE|30956-7^Vaccine Type^LN|2|21^Varicella^CVX||||||F|\rOBX|3|TS|29768-9^Date vaccine information statement published^LN|2|20080313||||||F|\rOBX|4|TS|29769-7^Date vaccine information statement presented^LN|2|20170530||||||F|","mqeCode":"MQE0260","count":48,"diagnosticMessage":"","source":"MQE"},{"severity":"ERROR","reportedMessage":"Patient name last is missing","hl7LocationList":[{"line":0,"segmentId":"PID","segmentSequence":1,"fieldPosition":5,"fieldRepetition":1,"componentNumber":1,"subComponentNumber":1,"baseReference":"PID-5.1.1","fieldLoc":"PID-5","abbreviated":"PID-5"}],"hl7ErrorCode":{"identifier":"101","text":"","nameOfCodingSystem":"","alternateIdentifier":"","alternateText":"","nameOfAlternateCodingSystem":""},"applicationErrorCode":{"identifier":"4","text":"Invalid value","nameOfCodingSystem":"HL70533","alternateIdentifier":"MQE0166","alternateText":"Patient name last is missing","nameOfAlternateCodingSystem":"L"},"reportedCount":126,"exampleMessage":"MSH|^~\\&|||||20170530103218-0600||VXU^V04^VXU_V04|3SUt-K.01.03.2dd|P|2.5.1|\rPID|||3SUt-K.01.03^^^AIRA-TEST^MR|||Mesta^Beata|20130604|M||2106-3^White^HL70005|377 Clark Ave^^Hamtramck^MI^48212^USA^P||^PRN^PH^^^313^6259761|||||||||2186-5^not Hispanic or Latino^HL70005|\rPD1|||||||||||02^Reminder/Recall - any method^HL70215|||||A|20170530|20170530|\rNK1|1|Mitchell^Beata^^^^^L|MTH^Mother^HL70063|377 Clark Ave^^Hamtramck^MI^48212^USA^P|^PRN^PH^^^313^6259761|\rORC|RE||T76N12.3^AIRA|||||||I-23432^Burden^Donna^A^^^^^NIST-AA-1||57422^RADON^NICHOLAS^^^^^^NIST-AA-1^L|\rRXA|0|1|20170530||03^MMR^CVX|0.5|mL^milliliters^UCUM||00^Administered^NIP001||||||V7634SH||MSD^Merck and Co^MVX||||A|\rRXR|SC^^HL70162|LA^^HL70163|\rOBX|1|CE|64994-7^Vaccine funding program eligibility category^LN|1|V03^VFC eligible - Uninsured^HL70064||||||F|||20170530|||VXC40^Eligibility captured at the immunization level^CDCPHINVS|\rOBX|2|CE|30956-7^Vaccine Type^LN|2|03^MMR^CVX||||||F|\rOBX|3|TS|29768-9^Date vaccine information statement published^LN|2|20120420||||||F|\rOBX|4|TS|29769-7^Date vaccine information statement presented^LN|2|20170530||||||F|","mqeCode":"MQE0166","count":126,"diagnosticMessage":"","source":"MQE"},{"severity":"ERROR","reportedMessage":"Vaccination admin code is not usable","hl7LocationList":[{"line":0,"segmentId":"RXA","segmentSequence":1,"fieldPosition":5,"fieldRepetition":1,"componentNumber":1,"subComponentNumber":1,"baseReference":"RXA-5.1.1","fieldLoc":"RXA-5","abbreviated":"RXA[1]-5"}],"hl7ErrorCode":{"identifier":"0","text":"","nameOfCodingSystem":"","alternateIdentifier":"","alternateText":"","nameOfAlternateCodingSystem":""},"applicationErrorCode":{"identifier":"4","text":"Invalid value","nameOfCodingSystem":"HL70533","alternateIdentifier":"MQE0561","alternateText":"Vaccination admin code is not usable","nameOfAlternateCodingSystem":"L"},"reportedCount":32,"exampleMessage":"MSH|^~\\&|||||20170530103220-0600||VXU^V04^VXU_V04|3SUt-C.01.49.47|P|2.5.1|\rPID|||3SUt-C.01.49^^^AIRA-TEST^MR||Berks^Laraine^^^^^L|Canadian^Shubha|20130527|F||2106-3^White^HL70005|106 Miami Pl^^Grand Rapids^MI^49519^USA^P||^PRN^PH^^^616^3801293|||||||||2186-5^not Hispanic or Latino^HL70005|\rPD1|||||||||||02^Reminder/Recall - any method^HL70215|||||A|20170530|20170530|\rNK1|1|Canadian^Shubha^^^^^L|MTH^Mother^HL70063|106 Miami Pl^^Grand Rapids^MI^49519^USA^P|^PRN^PH^^^616^3801293|\rORC|RE||U22W466.3^AIRA|||||||I-23432^Burden^Donna^A^^^^^NIST-AA-1||57422^RADON^NICHOLAS^^^^^^NIST-AA-1^L|\rRXA|0|1|20170530||PCV^MMR^CVX|0.5|mL^milliliters^UCUM||00^Administered^NIP001||||||Z7029FR||MSD^Merck and Co^MVX||||A|\rRXR|SC^^HL70162|LA^^HL70163|\rOBX|1|CE|64994-7^Vaccine funding program eligibility category^LN|1|V02^VFC eligible - Medicaid/Medicaid Managed Care^HL70064||||||F|||20170530|||VXC40^Eligibility captured at the immunization level^CDCPHINVS|\rOBX|2|CE|30956-7^Vaccine Type^LN|2|03^MMR^CVX||||||F|\rOBX|3|TS|29768-9^Date vaccine information statement published^LN|2|20120420||||||F|\rOBX|4|TS|29769-7^Date vaccine information statement presented^LN|2|20170530||||||F|","mqeCode":"MQE0561","count":32,"diagnosticMessage":"","source":"MQE"},{"severity":"ERROR","reportedMessage":"Vaccination admin date is missing","hl7LocationList":[{"line":0,"segmentId":"RXA","segmentSequence":1,"fieldPosition":3,"fieldRepetition":1,"componentNumber":1,"subComponentNumber":1,"baseReference":"RXA-3.1.1","fieldLoc":"RXA-3","abbreviated":"RXA[1]-3"}],"hl7ErrorCode":{"identifier":"101","text":"","nameOfCodingSystem":"","alternateIdentifier":"","alternateText":"","nameOfAlternateCodingSystem":""},"applicationErrorCode":{"identifier":"4","text":"Invalid value","nameOfCodingSystem":"HL70533","alternateIdentifier":"MQE0261","alternateText":"Vaccination admin date is missing","nameOfAlternateCodingSystem":"L"},"reportedCount":114,"exampleMessage":"MSH|^~\\&|||||20170530103218-0600||VXU^V04^VXU_V04|3SUt-K.01.08.2du|P|2.5.1|\rPID|||3SUt-K.01.08^^^AIRA-TEST^MR||Jepsen^Visala^Z^^^^L|Zavala^Nilima|20130511|F||2106-3^White^HL70005|90 McDonald Ln^^Brockway Township^MI^48097^USA^P||^PRN^PH^^^810^5634594|||||||||2186-5^not Hispanic or Latino^HL70005|\rPD1|||||||||||02^Reminder/Recall - any method^HL70215|||||A|20170530|20170530|\rNK1|1|Jepsen^Nilima^^^^^L|MTH^Mother^HL70063|90 McDonald Ln^^Brockway Township^MI^48097^USA^P|^PRN^PH^^^810^5634594|\rORC|RE||I95Z17.3^AIRA|||||||I-23432^Burden^Donna^A^^^^^NIST-AA-1||57422^RADON^NICHOLAS^^^^^^NIST-AA-1^L|\rRXA|0|1|||03^MMR^CVX|0.5|mL^milliliters^UCUM||00^Administered^NIP001||||||U1747GW||MSD^Merck and Co^MVX||||A|\rRXR|SC^^HL70162|LA^^HL70163|\rOBX|1|CE|64994-7^Vaccine funding program eligibility category^LN|1|V02^VFC eligible - Medicaid/Medicaid Managed Care^HL70064||||||F|||20170530|||VXC40^Eligibility captured at the immunization level^CDCPHINVS|\rOBX|2|CE|30956-7^Vaccine Type^LN|2|03^MMR^CVX||||||F|\rOBX|3|TS|29768-9^Date vaccine information statement published^LN|2|20120420||||||F|\rOBX|4|TS|29769-7^Date vaccine information statement presented^LN|2|20170530||||||F|","mqeCode":"MQE0261","count":114,"diagnosticMessage":"","source":"MQE"},{"severity":"ERROR","reportedMessage":"Patient name last is invalid","hl7LocationList":[{"line":0,"segmentId":"PID","segmentSequence":1,"fieldPosition":5,"fieldRepetition":1,"componentNumber":1,"subComponentNumber":1,"baseReference":"PID-5.1.1","fieldLoc":"PID-5","abbreviated":"PID-5"}],"hl7ErrorCode":{"identifier":"102","text":"","nameOfCodingSystem":"","alternateIdentifier":"","alternateText":"","nameOfAlternateCodingSystem":""},"applicationErrorCode":{"identifier":"4","text":"Invalid value","nameOfCodingSystem":"HL70533","alternateIdentifier":"MQE0165","alternateText":"Patient name last is invalid","nameOfAlternateCodingSystem":"L"},"reportedCount":12,"exampleMessage":"MSH|^~\\&|||||20170530103220-0600||VXU^V04^VXU_V04|3SUt-C.01.38.3J|P|2.5.1|\rPID|||3SUt-C.01.38^^^AIRA-TEST^MR||Apt #5^Warwick^Koora^^^^L|Fox^Thetis|20130527|M||2028-9^Asian^HL70005|159 Harper Ave^^Flint^MI^48554^USA^P||^PRN^PH^^^810^2449011|||||||||2186-5^not Hispanic or Latino^HL70005|\rPD1|||||||||||02^Reminder/Recall - any method^HL70215|||||A|20170530|20170530|\rNK1|1|Fox^Thetis^^^^^L|MTH^Mother^HL70063|159 Harper Ave^^Flint^MI^48554^USA^P|^PRN^PH^^^810^2449011|\rORC|RE||O86V455.3^AIRA|||||||I-23432^Burden^Donna^A^^^^^NIST-AA-1||57422^RADON^NICHOLAS^^^^^^NIST-AA-1^L|\rRXA|0|1|20170530||03^MMR^CVX|0.5|mL^milliliters^UCUM||00^Administered^NIP001||||||V7634SH||MSD^Merck and Co^MVX||||A|\rRXR|SC^^HL70162|LA^^HL70163|\rOBX|1|CE|64994-7^Vaccine funding program eligibility category^LN|1|V02^VFC eligible - Medicaid/Medicaid Managed Care^HL70064||||||F|||20170530|||VXC40^Eligibility captured at the immunization level^CDCPHINVS|\rOBX|2|CE|30956-7^Vaccine Type^LN|2|03^MMR^CVX||||||F|\rOBX|3|TS|29768-9^Date vaccine information statement published^LN|2|20120420||||||F|\rOBX|4|TS|29769-7^Date vaccine information statement presented^LN|2|20170530||||||F|","mqeCode":"MQE0165","count":12,"diagnosticMessage":"","source":"MQE"},{"severity":"ERROR","reportedMessage":"Vaccination admin date is before or after licensed vaccine range","hl7LocationList":[{"line":0,"segmentId":"RXA","segmentSequence":1,"fieldPosition":3,"fieldRepetition":1,"componentNumber":1,"subComponentNumber":1,"baseReference":"RXA-3.1.1","fieldLoc":"RXA-3","abbreviated":"RXA[1]-3"}],"hl7ErrorCode":{"identifier":"0","text":"","nameOfCodingSystem":"","alternateIdentifier":"","alternateText":"","nameOfAlternateCodingSystem":""},"applicationErrorCode":{"identifier":"3","text":"Illogical Value error","nameOfCodingSystem":"HL70533","alternateIdentifier":"MQE0257","alternateText":"Vaccination admin date is before or after licensed vaccine range","nameOfAlternateCodingSystem":"L"},"reportedCount":4681,"exampleMessage":"MSH|^~\\&|||||20170530103254-0600||VXU^V04^VXU_V04|3SUt-F.116.14136.15z|P|2.5.1|\rPID|||SUt-F.116.14136^^^AIRA-TEST^MR||Rose^Manjari^Phillida^^^^L|Pecos^Haliey|20050115|F||2076-8^Native Hawaiian or Other Pacific Islander^CDCREC|394 Lake St^^Good Hart^MI^49737^USA^P||^PRN^PH^^^616^4330519|||||||||2186-5^not Hispanic or Latino^CDCREC|\rNK1|1|Pecos^Haliey^^^^^L|MTH^Mother^HL70063|394 Lake St^^Good Hart^MI^49737^USA^P|^PRN^PH^^^616^4330519|\rORC|RE||111505^TCH-FT|\rRXA|0|1|20060115||120^DTaP-Hib-IPV^CVX|999|||01^Historical^NIP001|\rORC|RE||111506^TCH-FT|\rRXA|0|1|20110115||120^DTaP-Hib-IPV^CVX|999|||01^Historical^NIP001|","mqeCode":"MQE0257","count":4681,"diagnosticMessage":"","source":"MQE"},{"severity":"ERROR","reportedMessage":"Patient name first is missing","hl7LocationList":[{"line":0,"segmentId":"PID","segmentSequence":1,"fieldPosition":5,"fieldRepetition":1,"componentNumber":2,"subComponentNumber":1,"baseReference":"PID-5.2.1","fieldLoc":"PID-5","abbreviated":"PID-5.2"}],"hl7ErrorCode":{"identifier":"101","text":"","nameOfCodingSystem":"","alternateIdentifier":"","alternateText":"","nameOfAlternateCodingSystem":""},"applicationErrorCode":{"identifier":"4","text":"Invalid value","nameOfCodingSystem":"HL70533","alternateIdentifier":"MQE0141","alternateText":"Patient name first is missing","nameOfAlternateCodingSystem":"L"},"reportedCount":126,"exampleMessage":"MSH|^~\\&|||||20170530103218-0600||VXU^V04^VXU_V04|3SUt-K.01.03.2dd|P|2.5.1|\rPID|||3SUt-K.01.03^^^AIRA-TEST^MR|||Mesta^Beata|20130604|M||2106-3^White^HL70005|377 Clark Ave^^Hamtramck^MI^48212^USA^P||^PRN^PH^^^313^6259761|||||||||2186-5^not Hispanic or Latino^HL70005|\rPD1|||||||||||02^Reminder/Recall - any method^HL70215|||||A|20170530|20170530|\rNK1|1|Mitchell^Beata^^^^^L|MTH^Mother^HL70063|377 Clark Ave^^Hamtramck^MI^48212^USA^P|^PRN^PH^^^313^6259761|\rORC|RE||T76N12.3^AIRA|||||||I-23432^Burden^Donna^A^^^^^NIST-AA-1||57422^RADON^NICHOLAS^^^^^^NIST-AA-1^L|\rRXA|0|1|20170530||03^MMR^CVX|0.5|mL^milliliters^UCUM||00^Administered^NIP001||||||V7634SH||MSD^Merck and Co^MVX||||A|\rRXR|SC^^HL70162|LA^^HL70163|\rOBX|1|CE|64994-7^Vaccine funding program eligibility category^LN|1|V03^VFC eligible - Uninsured^HL70064||||||F|||20170530|||VXC40^Eligibility captured at the immunization level^CDCPHINVS|\rOBX|2|CE|30956-7^Vaccine Type^LN|2|03^MMR^CVX||||||F|\rOBX|3|TS|29768-9^Date vaccine information statement published^LN|2|20120420||||||F|\rOBX|4|TS|29769-7^Date vaccine information statement presented^LN|2|20170530||||||F|","mqeCode":"MQE0141","count":126,"diagnosticMessage":"","source":"MQE"},{"severity":"ERROR","reportedMessage":"Vaccination admin date is after message submitted","hl7LocationList":[{"line":0,"segmentId":"RXA","segmentSequence":1,"fieldPosition":3,"fieldRepetition":1,"componentNumber":1,"subComponentNumber":1,"baseReference":"RXA-3.1.1","fieldLoc":"RXA-3","abbreviated":"RXA[1]-3"}],"hl7ErrorCode":{"identifier":"0","text":"","nameOfCodingSystem":"","alternateIdentifier":"","alternateText":"","nameOfAlternateCodingSystem":""},"applicationErrorCode":{"identifier":"1","text":"Illogical Date error","nameOfCodingSystem":"HL70533","alternateIdentifier":"MQE0252","alternateText":"Vaccination admin date is after message submitted","nameOfAlternateCodingSystem":"L"},"reportedCount":424,"exampleMessage":"MSH|^~\\&|||||20170530103254-0600||VXU^V04^VXU_V04|3SUt-F.116.14602.1gr|P|2.5.1|\rPID|||SUt-F.116.14602^^^AIRA-TEST^MR||Tuscola^Ariane^^^^^L|Susas^Wallis|20110101|F||2054-5^Black or African-American^CDCREC|53 Marion Cir^^Hudson^MI^49247^USA^P||^PRN^PH^^^517^9208627|||||||||2135-2^Hispanic or Latino^CDCREC|\rNK1|1|Tuscola^Wallis^^^^^L|MTH^Mother^HL70063|53 Marion Cir^^Hudson^MI^49247^USA^P|^PRN^PH^^^517^9208627|\rORC|RE||112582^TCH-FT|\rRXA|0|1|20130922||120^DTaP-Hib-IPV^CVX|999|||01^Historical^NIP001|\rORC|RE||112583^TCH-FT|\rRXA|0|1|20171215||120^DTaP-Hib-IPV^CVX|999|||01^Historical^NIP001|","mqeCode":"MQE0252","count":424,"diagnosticMessage":"","source":"MQE"},{"severity":"ERROR","reportedMessage":"Patient birth date is missing","hl7LocationList":[{"line":0,"segmentId":"PID","segmentSequence":1,"fieldPosition":7,"fieldRepetition":1,"componentNumber":1,"subComponentNumber":1,"baseReference":"PID-7.1.1","fieldLoc":"PID-7","abbreviated":"PID-7"}],"hl7ErrorCode":{"identifier":"101","text":"","nameOfCodingSystem":"","alternateIdentifier":"","alternateText":"","nameOfAlternateCodingSystem":""},"applicationErrorCode":{"identifier":"4","text":"Invalid value","nameOfCodingSystem":"HL70533","alternateIdentifier":"MQE0118","alternateText":"Patient birth date is missing","nameOfAlternateCodingSystem":"L"},"reportedCount":121,"exampleMessage":"MSH|^~\\&|||||20170530103218-0600||VXU^V04^VXU_V04|3SUt-K.01.04.2dh|P|2.5.1|\rPID|||3SUt-K.01.04^^^AIRA-TEST^MR||Callahan^Tabitha^O^^^^L|La Paz^Cailin||F||2106-3^White^HL70005|147 Johnson Cir^^Whitmore Lake^MI^48189^USA^P||^PRN^PH^^^734^8925300|||||||||2186-5^not Hispanic or Latino^HL70005|\rPD1|||||||||||02^Reminder/Recall - any method^HL70215|||||A|20170530|20170530|\rNK1|1|Callahan^Cailin^^^^^L|MTH^Mother^HL70063|147 Johnson Cir^^Whitmore Lake^MI^48189^USA^P|^PRN^PH^^^734^8925300|\rORC|RE||V80F13.3^AIRA|||||||I-23432^Burden^Donna^A^^^^^NIST-AA-1||57422^RADON^NICHOLAS^^^^^^NIST-AA-1^L|\rRXA|0|1|20170530||03^MMR^CVX|0.5|mL^milliliters^UCUM||00^Administered^NIP001||||||U1747GW||MSD^Merck and Co^MVX||||A|\rRXR|SC^^HL70162|LA^^HL70163|\rOBX|1|CE|64994-7^Vaccine funding program eligibility category^LN|1|V02^VFC eligible - Medicaid/Medicaid Managed Care^HL70064||||||F|||20170530|||VXC40^Eligibility captured at the immunization level^CDCPHINVS|\rOBX|2|CE|30956-7^Vaccine Type^LN|2|03^MMR^CVX||||||F|\rOBX|3|TS|29768-9^Date vaccine information statement published^LN|2|20120420||||||F|\rOBX|4|TS|29769-7^Date vaccine information statement presented^LN|2|20170530||||||F|","mqeCode":"MQE0118","count":121,"diagnosticMessage":"","source":"MQE"},{"severity":"ERROR","reportedMessage":"Patient birth date is after submission","hl7LocationList":[{"line":0,"segmentId":"PID","segmentSequence":1,"fieldPosition":7,"fieldRepetition":1,"componentNumber":1,"subComponentNumber":1,"baseReference":"PID-7.1.1","fieldLoc":"PID-7","abbreviated":"PID-7"}],"hl7ErrorCode":{"identifier":"0","text":"","nameOfCodingSystem":"","alternateIdentifier":"","alternateText":"","nameOfAlternateCodingSystem":""},"applicationErrorCode":{"identifier":"1","text":"Illogical Date error","nameOfCodingSystem":"HL70533","alternateIdentifier":"MQE0115","alternateText":"Patient birth date is after submission","nameOfAlternateCodingSystem":"L"},"reportedCount":44,"exampleMessage":"MSH|^~\\&|||||20170530103220-0600||VXU^V04^VXU_V04|3SUt-C.01.21.3b|P|2.5.1|\rPID|||3SUt-C.01.21^^^AIRA-TEST^MR||Harney^Olono^Rini^^^^L|Thurston^Sashenka|20180530|F||2106-3^White^HL70005|244 Simpson Pl^^Sodus^MI^49126^USA^P||^PRN^PH^^^269^9486443|||||||||2135-2^Hispanic or Latino^HL70005|\rPD1|||||||||||02^Reminder/Recall - any method^HL70215|||||A|20170530|20170530|\rNK1|1|Harney^Sashenka^^^^^L|MTH^Mother^HL70063|244 Simpson Pl^^Sodus^MI^49126^USA^P|^PRN^PH^^^269^9486443|\rORC|RE||S63I438.3^AIRA|||||||I-23432^Burden^Donna^A^^^^^NIST-AA-1||57422^RADON^NICHOLAS^^^^^^NIST-AA-1^L|\rRXA|0|1|20170530||03^MMR^CVX|0.5|mL^milliliters^UCUM||00^Administered^NIP001||||||Z7029FR||MSD^Merck and Co^MVX||||A|\rRXR|SC^^HL70162|LA^^HL70163|\rOBX|1|CE|64994-7^Vaccine funding program eligibility category^LN|1|V02^VFC eligible - Medicaid/Medicaid Managed Care^HL70064||||||F|||20170530|||VXC40^Eligibility captured at the immunization level^CDCPHINVS|\rOBX|2|CE|30956-7^Vaccine Type^LN|2|03^MMR^CVX||||||F|\rOBX|3|TS|29768-9^Date vaccine information statement published^LN|2|20120420||||||F|\rOBX|4|TS|29769-7^Date vaccine information statement presented^LN|2|20170530||||||F|","mqeCode":"MQE0115","count":44,"diagnosticMessage":"","source":"MQE"}],"codeIssues":[{"typeCode":"MESSAGE_ACCEPT_ACK_TYPE","typeName":"Acknowledgement Type","source":"MSH-15","attribute":"","value":"SOMETIMES","count":12,"exampleMessage":"MSH|^~\\&|||||20170530103220-0600||VXU^V04^VXU_V04|3SUt-C.02.69.4V|P|2.5.1|||SOMETIMES|\rPID|||3SUt-C.02.69^^^AIRA-TEST^MR||Greenup^Kristy^Tamatha^^^^L|Grant^Iona|20130528|F||2106-3^White^HL70005|103 Iron Ave^^Winn^MI^48896^USA^P||^PRN^PH^^^989^2379242|||||||||2186-5^not Hispanic or Latino^HL70005|\rPD1|||||||||||02^Reminder/Recall - any method^HL70215|||||A|20170530|20170530|\rNK1|1|Greenup^Iona^^^^^L|MTH^Mother^HL70063|103 Iron Ave^^Winn^MI^48896^USA^P|^PRN^PH^^^989^2379242|\rORC|RE||U38P486.3^AIRA|||||||I-23432^Burden^Donna^A^^^^^NIST-AA-1||57422^RADON^NICHOLAS^^^^^^NIST-AA-1^L|\rRXA|0|1|20170530||03^MMR^CVX|0.5|mL^milliliters^UCUM||00^Administered^NIP001||||||Z7029FR||MSD^Merck and Co^MVX||||A|\rRXR|SC^^HL70162|LA^^HL70163|\rOBX|1|CE|64994-7^Vaccine funding program eligibility category^LN|1|V03^VFC eligible - Uninsured^HL70064||||||F|||20170530|||VXC40^Eligibility captured at the immunization level^CDCPHINVS|\rOBX|2|CE|30956-7^Vaccine Type^LN|2|03^MMR^CVX||||||F|\rOBX|3|TS|29768-9^Date vaccine information statement published^LN|2|20120420||||||F|\rOBX|4|TS|29769-7^Date vaccine information statement presented^LN|2|20170530||||||F|","status":"Unrecognized","label":null},{"typeCode":"MESSAGE_ACCEPT_ACK_TYPE","typeName":"Acknowledgement Type","source":"MSH-15","attribute":"","value":"Monday","count":12,"exampleMessage":"MSH|^~\\&|||||20170530103220-0600||VXU^V04^VXU_V04|3SUt-C.02.70.4X|P|2.5.1||||Monday|\rPID|||3SUt-C.02.70^^^AIRA-TEST^MR||Mahaska^Rearden^Dillon^^^^L|Ida^Karel|20130524|M||2106-3^White^HL70005|82 Tuscarawas St^^Mackinac Island^MI^49757^USA^P||^PRN^PH^^^906^3428726|||||||||2135-2^Hispanic or Latino^HL70005|\rPD1|||||||||||02^Reminder/Recall - any method^HL70215|||||A|20170530|20170530|\rNK1|1|Mahaska^Karel^^^^^L|MTH^Mother^HL70063|82 Tuscarawas St^^Mackinac Island^MI^49757^USA^P|^PRN^PH^^^906^3428726|\rORC|RE||H39D487.3^AIRA|||||||I-23432^Burden^Donna^A^^^^^NIST-AA-1||57422^RADON^NICHOLAS^^^^^^NIST-AA-1^L|\rRXA|0|1|20170530||03^MMR^CVX|0.5|mL^milliliters^UCUM||00^Administered^NIP001||||||P3400YX||MSD^Merck and Co^MVX||||A|\rRXR|SC^^HL70162|LA^^HL70163|\rOBX|1|CE|64994-7^Vaccine funding program eligibility category^LN|1|V02^VFC eligible - Medicaid/Medicaid Managed Care^HL70064||||||F|||20170530|||VXC40^Eligibility captured at the immunization level^CDCPHINVS|\rOBX|2|CE|30956-7^Vaccine Type^LN|2|03^MMR^CVX||||||F|\rOBX|3|TS|29768-9^Date vaccine information statement published^LN|2|20120420||||||F|\rOBX|4|TS|29769-7^Date vaccine information statement presented^LN|2|20170530||||||F|","status":"Unrecognized","label":null},{"typeCode":"NEXT_OF_KIN_ADDRESS_TYPE","typeName":"Address Type","source":"NK1-4.7","attribute":"","value":"PRIMARY","count":12,"exampleMessage":"MSH|^~\\&|||||20170530103220-0600||VXU^V04^VXU_V04|3SUt-C.02.94.5M|P|2.5.1|\rPID|||3SUt-C.02.94^^^AIRA-TEST^MR||Pulaski^Malise^L^^^^L|Lassen^Volante|20130528|F||2106-3^White^HL70005|127 Dundy Pl^^East Lansing^MI^48826^USA^P||^PRN^PH^^^517^9901309|||||||||2186-5^not Hispanic or Latino^HL70005|\rPD1|||||||||||02^Reminder/Recall - any method^HL70215|||||A|20170530|20170530|\rNK1|1|Charlevoix^Volante^^^^^L|MTH^Mother^HL70063|127 Dundy Pl^^East Lansing^MI^48826^USA^PRIMARY|^PRN^PH^^^517^9901309|\rORC|RE||E98A511.3^AIRA|||||||I-23432^Burden^Donna^A^^^^^NIST-AA-1||57422^RADON^NICHOLAS^^^^^^NIST-AA-1^L|\rRXA|0|1|20170530||21^Varicella^CVX|0.5|mL^milliliters^UCUM||00^Administered^NIP001||||||N3783EO||MSD^Merck and Co^MVX||||A|\rRXR|SC^^HL70162|RA^^HL70163|\rOBX|1|CE|64994-7^Vaccine funding program eligibility category^LN|1|V04^VFC eligible - American Indian/Alaskan Native^HL70064||||||F|||20170530|||VXC40^Eligibility captured at the immunization level^CDCPHINVS|\rOBX|2|CE|30956-7^Vaccine Type^LN|2|21^Varicella^CVX||||||F|\rOBX|3|TS|29768-9^Date vaccine information statement published^LN|2|20080313||||||F|\rOBX|4|TS|29769-7^Date vaccine information statement presented^LN|2|20170530||||||F|","status":"Unrecognized","label":null},{"typeCode":"PATIENT_ADDRESS_TYPE","typeName":"Address Type","source":"PID-11.7","attribute":"","value":"PRIMARY","count":12,"exampleMessage":"MSH|^~\\&|||||20170530103220-0600||VXU^V04^VXU_V04|3SUt-C.02.94.5M|P|2.5.1|\rPID|||3SUt-C.02.94^^^AIRA-TEST^MR||Pulaski^Malise^L^^^^L|Lassen^Volante|20130528|F||2106-3^White^HL70005|127 Dundy Pl^^East Lansing^MI^48826^USA^P||^PRN^PH^^^517^9901309|||||||||2186-5^not Hispanic or Latino^HL70005|\rPD1|||||||||||02^Reminder/Recall - any method^HL70215|||||A|20170530|20170530|\rNK1|1|Charlevoix^Volante^^^^^L|MTH^Mother^HL70063|127 Dundy Pl^^East Lansing^MI^48826^USA^PRIMARY|^PRN^PH^^^517^9901309|\rORC|RE||E98A511.3^AIRA|||||||I-23432^Burden^Donna^A^^^^^NIST-AA-1||57422^RADON^NICHOLAS^^^^^^NIST-AA-1^L|\rRXA|0|1|20170530||21^Varicella^CVX|0.5|mL^milliliters^UCUM||00^Administered^NIP001||||||N3783EO||MSD^Merck and Co^MVX||||A|\rRXR|SC^^HL70162|RA^^HL70163|\rOBX|1|CE|64994-7^Vaccine funding program eligibility category^LN|1|V04^VFC eligible - American Indian/Alaskan Native^HL70064||||||F|||20170530|||VXC40^Eligibility captured at the immunization level^CDCPHINVS|\rOBX|2|CE|30956-7^Vaccine Type^LN|2|21^Varicella^CVX||||||F|\rOBX|3|TS|29768-9^Date vaccine information statement published^LN|2|20080313||||||F|\rOBX|4|TS|29769-7^Date vaccine information statement presented^LN|2|20170530||||||F|","status":"Unrecognized","label":null},{"typeCode":"VACCINATION_ADMINISTERED_UNIT","typeName":"Administration Unit","source":"RXA-7","attribute":"Administered","value":"CM","count":6,"exampleMessage":"MSH|^~\\&|||||20170530103220-0600||VXU^V04^VXU_V04|3SUt-C.02.181.9J|P|2.5.1|\rPID|||3SUt-C.02.181^^^AIRA-TEST^MR||Dickinson^Fatima^Cherry^^^^L|Fayette^Corliss|20130524|F||2054-5^Black or African-American^HL70005|67 Keya Paha Cir^^Belmont^MI^49306^USA^P||^PRN^PH^^^616^4141489|||||||||2186-5^not Hispanic or Latino^HL70005|\rPD1|||||||||||02^Reminder/Recall - any method^HL70215|||||A|20170530|20170530|\rNK1|1|Dickinson^Corliss^^^^^L|MTH^Mother^HL70063|67 Keya Paha Cir^^Belmont^MI^49306^USA^P|^PRN^PH^^^616^4141489|\rORC|RE||S18F598.3^AIRA|||||||I-23432^Burden^Donna^A^^^^^NIST-AA-1||57422^RADON^NICHOLAS^^^^^^NIST-AA-1^L|\rRXA|0|1|20170530||21^Varicella^CVX|0.5|CM^milliliters^ISO+||00^Administered^NIP001||||||U6329BP||MSD^Merck and Co^MVX||||A|\rRXR|SC^^HL70162|RA^^HL70163|\rOBX|1|CE|64994-7^Vaccine funding program eligibility category^LN|1|V04^VFC eligible - American Indian/Alaskan Native^HL70064||||||F|||20170530|||VXC40^Eligibility captured at the immunization level^CDCPHINVS|\rOBX|2|CE|30956-7^Vaccine Type^LN|2|21^Varicella^CVX||||||F|\rOBX|3|TS|29768-9^Date vaccine information statement published^LN|2|20080313||||||F|\rOBX|4|TS|29769-7^Date vaccine information statement presented^LN|2|20170530||||||F|","status":"Unrecognized","label":null},{"typeCode":"PATIENT_BIRTH_ORDER","typeName":"Birth Order","source":"PID-25","attribute":"","value":"Twin","count":12,"exampleMessage":"MSH|^~\\&|||||20170530103220-0600||VXU^V04^VXU_V04|3SUt-C.02.123.6R|P|2.5.1|\rPID|||3SUt-C.02.123^^^AIRA-TEST^MR||Hunt^Hugo^J^^^^L|Hardin^Vesper|20130526|M||2131-1^Other Race^HL70005|330 Lamar St^^Riley^MI^48041^USA^P||^PRN^PH^^^810^7942838|||||||||2186-5^not Hispanic or Latino^HL70005||Y|Twin|\rPD1|||||||||||02^Reminder/Recall - any method^HL70215|||||A|20170530|20170530|\rNK1|1|Hunt^Vesper^^^^^L|MTH^Mother^HL70063|330 Lamar St^^Riley^MI^48041^USA^P|^PRN^PH^^^810^7942838|\rORC|RE||D72Z540.3^AIRA|||||||I-23432^Burden^Donna^A^^^^^NIST-AA-1||57422^RADON^NICHOLAS^^^^^^NIST-AA-1^L|\rRXA|0|1|20170530||21^Varicella^CVX|0.5|mL^milliliters^UCUM||00^Administered^NIP001||||||U6329BP||MSD^Merck and Co^MVX||||A|\rRXR|SC^^HL70162|RA^^HL70163|\rOBX|1|CE|64994-7^Vaccine funding program eligibility category^LN|1|V01^Not VFC eligible^HL70064||||||F|||20170530|||VXC40^Eligibility captured at the immunization level^CDCPHINVS|\rOBX|2|CE|30956-7^Vaccine Type^LN|2|21^Varicella^CVX||||||F|\rOBX|3|TS|29768-9^Date vaccine information statement published^LN|2|20080313||||||F|\rOBX|4|TS|29769-7^Date vaccine information statement presented^LN|2|20170530||||||F|","status":"Unrecognized","label":null},{"typeCode":"VACCINATION_BODY_ROUTE","typeName":"Body Route","source":"RXR-1","attribute":"Administered","value":"IN","count":21,"exampleMessage":"MSH|^~\\&|||||20170530103219-0600||VXU^V04^VXU_V04|3SUt-B.19.11.2oF|P|2.5.1|\rPID|||3SUt-B.19.11^^^AIRA-TEST^MR||Page^Sriram^Aeneas^^^^L|Preston^Nirvana|20130525|M||2028-9^Asian^HL70005|142 Saunders Ave^^Hulbert^MI^49748^USA^P||^PRN^PH^^^906^2477928|||||||||2186-5^not Hispanic or Latino^HL70005|\rPD1|||||||||||02^Reminder/Recall - any method^HL70215|||||A|20170530|20170530|\rNK1|1|Page^Nirvana^^^^^L|MTH^Mother^HL70063|142 Saunders Ave^^Hulbert^MI^49748^USA^P|^PRN^PH^^^906^2477928|\rORC|RE||W09F168.3^AIRA|||||||I-23432^Burden^Donna^A^^^^^NIST-AA-1||57422^RADON^NICHOLAS^^^^^^NIST-AA-1^L|\rRXA|0|1|20170530||94^MMRV^CVX|0.5|mL^milliliters^UCUM||00^Administered^NIP001||||||S4121RG||MSD^Merck and Co^MVX||||A|\rRXR|IN^Intranasal^HL70162|RA^^HL70163|\rOBX|1|CE|64994-7^Vaccine funding program eligibility category^LN|1|V03^VFC eligible - Uninsured^HL70064||||||F|||20170530|||VXC40^Eligibility captured at the immunization level^CDCPHINVS|\rOBX|2|CE|30956-7^Vaccine Type^LN|2|94^MMRV^CVX||||||F|\rOBX|3|TS|29768-9^Date vaccine information statement published^LN|2|20100521||||||F|\rOBX|4|TS|29769-7^Date vaccine information statement presented^LN|2|20170530||||||F|","status":"Deprecated","label":"Intranasal"},{"typeCode":"VACCINATION_BODY_ROUTE","typeName":"Body Route","source":"RXR-1","attribute":"Administered","value":"MMR","count":6,"exampleMessage":"MSH|^~\\&|||||20170530103220-0600||VXU^V04^VXU_V04|3SUt-C.02.184.9Q|P|2.5.1|\rPID|||3SUt-C.02.184^^^AIRA-TEST^MR||Butte^Stacy^Dione^^^^L|Spencer^Berenice|20130612|F||2106-3^White^HL70005|340 Delta St^^Northwest^MI^48504^USA^P||^PRN^PH^^^810^3905908|||||||||2186-5^not Hispanic or Latino^HL70005|\rPD1|||||||||||02^Reminder/Recall - any method^HL70215|||||A|20170530|20170530|\rNK1|1|Butte^Berenice^^^^^L|MTH^Mother^HL70063|340 Delta St^^Northwest^MI^48504^USA^P|^PRN^PH^^^810^3905908|\rORC|RE||B26K601.3^AIRA|||||||I-23432^Burden^Donna^A^^^^^NIST-AA-1||57422^RADON^NICHOLAS^^^^^^NIST-AA-1^L|\rRXA|0|1|20170530||03^MMR^CVX|0.5|mL^milliliters^UCUM||00^Administered^NIP001||||||P3400YX||MSD^Merck and Co^MVX||||A|\rRXR|MMR^^HL70162|LA^^HL70163|\rOBX|1|CE|64994-7^Vaccine funding program eligibility category^LN|1|V02^VFC eligible - Medicaid/Medicaid Managed Care^HL70064||||||F|||20170530|||VXC40^Eligibility captured at the immunization level^CDCPHINVS|\rOBX|2|CE|30956-7^Vaccine Type^LN|2|03^MMR^CVX||||||F|\rOBX|3|TS|29768-9^Date vaccine information statement published^LN|2|20120420||||||F|\rOBX|4|TS|29769-7^Date vaccine information statement presented^LN|2|20170530||||||F|","status":"Unrecognized","label":null},{"typeCode":"VACCINATION_BODY_SITE","typeName":"Body Site","source":"RXR-2","attribute":"Administered","value":"Jones Clinic","count":6,"exampleMessage":"MSH|^~\\&|||||20170530103220-0600||VXU^V04^VXU_V04|3SUt-C.02.186.9T|P|2.5.1|\rPID|||3SUt-C.02.186^^^AIRA-TEST^MR||Wyandot^Duncan^Kenelm^^^^L|Delta^Mariabella|20130530|M||2106-3^White^HL70005|16 Hart Pl^^Ecorse^MI^48229^USA^P||^PRN^PH^^^313^8550945|||||||||2186-5^not Hispanic or Latino^HL70005|\rPD1|||||||||||02^Reminder/Recall - any method^HL70215|||||A|20170530|20170530|\rNK1|1|Livingston^Mariabella^^^^^L|MTH^Mother^HL70063|16 Hart Pl^^Ecorse^MI^48229^USA^P|^PRN^PH^^^313^8550945|\rORC|RE||G47R603.3^AIRA|||||||I-23432^Burden^Donna^A^^^^^NIST-AA-1||57422^RADON^NICHOLAS^^^^^^NIST-AA-1^L|\rRXA|0|1|20170530||21^Varicella^CVX|0.5|mL^milliliters^UCUM||00^Administered^NIP001||||||G3407KC||MSD^Merck and Co^MVX||||A|\rRXR|SC^^HL70162|Jones Clinic^^|\rOBX|1|CE|64994-7^Vaccine funding program eligibility category^LN|1|V02^VFC eligible - Medicaid/Medicaid Managed Care^HL70064||||||F|||20170530|||VXC40^Eligibility captured at the immunization level^CDCPHINVS|\rOBX|2|CE|30956-7^Vaccine Type^LN|2|21^Varicella^CVX||||||F|\rOBX|3|TS|29768-9^Date vaccine information statement published^LN|2|20080313||||||F|\rOBX|4|TS|29769-7^Date vaccine information statement presented^LN|2|20170530||||||F|","status":"Unrecognized","label":null},{"typeCode":"VACCINATION_FINANCIAL_ELIGIBILITY_CODE","typeName":"Financial Status Code","source":"OBX-5","attribute":"Administered","value":"V00","count":12,"exampleMessage":"MSH|^~\\&|||||20170530103220-0600||VXU^V04^VXU_V04|3SUt-C.01.60.4C|P|2.5.1|\rPID|||3SUt-C.01.60^^^AIRA-TEST^MR||Harrison^Deiondre^^^^^L|Carlisle^Juana|20130602|F||2054-5^Black or African-American^HL70005|106 Lucas Pl^^Clay Township^MI^48001^USA^P||^PRN^PH^^^810^2033057|||||||||2186-5^not Hispanic or Latino^HL70005|\rPD1|||||||||||02^Reminder/Recall - any method^HL70215|||||A|20170530|20170530|\rNK1|1|Cummings^Juana^^^^^L|MTH^Mother^HL70063|106 Lucas Pl^^Clay Township^MI^48001^USA^P|^PRN^PH^^^810^2033057|\rORC|RE||M10J477.3^AIRA|||||||I-23432^Burden^Donna^A^^^^^NIST-AA-1||57422^RADON^NICHOLAS^^^^^^NIST-AA-1^L|\rRXA|0|1|20170530||03^MMR^CVX|0.5|mL^milliliters^UCUM||00^Administered^NIP001||||||Z7029FR||MSD^Merck and Co^MVX||||A|\rRXR|SC^^HL70162|LA^^HL70163|\rOBX|1|CE|64994-7^Vaccine funding program eligibility category^LN|1|V00^VFC eligibility unknown^HL70064||||||F|||20170530|||VXC40^Eligibility captured at the immunization level^CDCPHINVS|\rOBX|2|CE|30956-7^Vaccine Type^LN|2|03^MMR^CVX||||||F|\rOBX|3|TS|29768-9^Date vaccine information statement published^LN|2|20120420||||||F|\rOBX|4|TS|29769-7^Date vaccine information statement presented^LN|2|20170530||||||F|","status":"Invalid","label":"VFC eligibility unknown"},{"typeCode":"VACCINATION_FINANCIAL_ELIGIBILITY_CODE","typeName":"Financial Status Code","source":"OBX-5","attribute":"Administered","value":"ZZZ01","count":12,"exampleMessage":"MSH|^~\\&|||||20170530103220-0600||VXU^V04^VXU_V04|3SUt-C.01.62.4G|P|2.5.1|\rPID|||3SUt-C.01.62^^^AIRA-TEST^MR||Taylor^Babar^L^^^^L|Van Wert^Ximena|20130529|M||2076-8^Native Hawaiian or Other Pacific Islander^HL70005|259 Sowden Ave^^Grand Rapids^MI^49512^USA^P||^PRN^PH^^^616^6246340|||||||||2186-5^not Hispanic or Latino^HL70005|\rPD1|||||||||||02^Reminder/Recall - any method^HL70215|||||A|20170530|20170530|\rNK1|1|Taylor^Ximena^^^^^L|MTH^Mother^HL70063|259 Sowden Ave^^Grand Rapids^MI^49512^USA^P|^PRN^PH^^^616^6246340|\rORC|RE||N82G479.3^AIRA|||||||I-23432^Burden^Donna^A^^^^^NIST-AA-1||57422^RADON^NICHOLAS^^^^^^NIST-AA-1^L|\rRXA|0|1|20170530||21^Varicella^CVX|0.5|mL^milliliters^UCUM||00^Administered^NIP001||||||U6329BP||MSD^Merck and Co^MVX||||A|\rRXR|SC^^HL70162|RA^^HL70163|\rOBX|1|CE|64994-7^Vaccine funding program eligibility category^LN|1|ZZZ01^VFC Eligible^||||||F|||20170530|||VXC40^Eligibility captured at the immunization level^CDCPHINVS|\rOBX|2|CE|30956-7^Vaccine Type^LN|2|21^Varicella^CVX||||||F|\rOBX|3|TS|29768-9^Date vaccine information statement published^LN|2|20080313||||||F|\rOBX|4|TS|29769-7^Date vaccine information statement presented^LN|2|20170530||||||F|","status":"Unrecognized","label":null},{"typeCode":"PATIENT_ETHNICITY","typeName":"Patient Ethnicity","source":"PID-22","attribute":"","value":"H","count":27,"exampleMessage":"MSH|^~\\&|||||20170530103220-0600||VXU^V04^VXU_V04|3SUt-C.02.129.79|P|2.5.1|\rPID|||3SUt-C.02.129^^^AIRA-TEST^MR||Simpson^Becse^Malvern^^^^L|Summresgill^Zhalore|20130529|M||2131-1^Other Race^HL70005|343 Garden Ave^^Jackson^MI^49203^USA^P||^PRN^PH^^^517^5869711|||||||||H^not Hispanic or Latino^HL70005|\rPD1|||||||||||02^Reminder/Recall - any method^HL70215|||||A|20170530|20170530|\rNK1|1|Summresgill^Zhalore^^^^^L|MTH^Mother^HL70063|343 Garden Ave^^Jackson^MI^49203^USA^P|^PRN^PH^^^517^5869711|\rORC|RE||A13R546.3^AIRA|||||||I-23432^Burden^Donna^A^^^^^NIST-AA-1||57422^RADON^NICHOLAS^^^^^^NIST-AA-1^L|\rRXA|0|1|20170530||21^Varicella^CVX|0.5|mL^milliliters^UCUM||00^Administered^NIP001||||||U6329BP||MSD^Merck and Co^MVX||||A|\rRXR|SC^^HL70162|RA^^HL70163|\rOBX|1|CE|64994-7^Vaccine funding program eligibility category^LN|1|V03^VFC eligible - Uninsured^HL70064||||||F|||20170530|||VXC40^Eligibility captured at the immunization level^CDCPHINVS|\rOBX|2|CE|30956-7^Vaccine Type^LN|2|21^Varicella^CVX||||||F|\rOBX|3|TS|29768-9^Date vaccine information statement published^LN|2|20080313||||||F|\rOBX|4|TS|29769-7^Date vaccine information statement presented^LN|2|20170530||||||F|","status":"Deprecated","label":"Hispanic or Latino"},{"typeCode":"PATIENT_ETHNICITY","typeName":"Patient Ethnicity","source":"PID-22","attribute":"","value":"N","count":16,"exampleMessage":"MSH|^~\\&|||||20170530103218-0600||VXU^V04^VXU_V04|3SUt-B.04.08.2kw|P|2.5.1|\rPID|||3SUt-B.04.08^^^AIRA-TEST^MR||Monona^Soren^^^^^L|Cassia^Zulema|20130525|M||2106-3^White^HL70005|87 Uvalde Ln^^Gould City^MI^49838^USA^P||^PRN^PH^^^906^3917801|||||||||N^not Hispanic or Latino^HL70189|\rPD1|||||||||||02^Reminder/Recall - any method^HL70215|||||A|20170530|20170530|\rNK1|1|Anning^Zulema^^^^^L|MTH^Mother^HL70063|87 Uvalde Ln^^Gould City^MI^49838^USA^P|^PRN^PH^^^906^3917801|\rORC|RE||Y27D57.3^AIRA|||||||I-23432^Burden^Donna^A^^^^^NIST-AA-1||57422^RADON^NICHOLAS^^^^^^NIST-AA-1^L|\rRXA|0|1|20170530||03^MMR^CVX|0.5|mL^milliliters^UCUM||00^Administered^NIP001||||||P3400YX||MSD^Merck and Co^MVX||||A|\rRXR|SC^^HL70162|LA^^HL70163|\rOBX|1|CE|64994-7^Vaccine funding program eligibility category^LN|1|V02^VFC eligible - Medicaid/Medicaid Managed Care^HL70064||||||F|||20170530|||VXC40^Eligibility captured at the immunization level^CDCPHINVS|\rOBX|2|CE|30956-7^Vaccine Type^LN|2|03^MMR^CVX||||||F|\rOBX|3|TS|29768-9^Date vaccine information statement published^LN|2|20120420||||||F|\rOBX|4|TS|29769-7^Date vaccine information statement presented^LN|2|20170530||||||F|","status":"Deprecated","label":"not Hispanic or Latino"},{"typeCode":"PATIENT_ETHNICITY","typeName":"Patient Ethnicity","source":"PID-22","attribute":"","value":"U","count":16,"exampleMessage":"MSH|^~\\&|||||20170530103218-0600||VXU^V04^VXU_V04|3SUt-B.04.09.2kz|P|2.5.1|\rPID|||3SUt-B.04.09^^^AIRA-TEST^MR||Leelanau^Brie^T^^^^L|Barker^Neka|20130521|F||1002-5^American Indian or Alaska Native^HL70005|142 Grant Ln^^Edwardsburg^MI^49112^USA^P||^PRN^PH^^^269^6588217|||||||||U^Unknown^HL70189|\rPD1|||||||||||02^Reminder/Recall - any method^HL70215|||||A|20170530|20170530|\rNK1|1|Leelanau^Neka^^^^^L|MTH^Mother^HL70063|142 Grant Ln^^Edwardsburg^MI^49112^USA^P|^PRN^PH^^^269^6588217|\rORC|RE||U67B58.3^AIRA|||||||I-23432^Burden^Donna^A^^^^^NIST-AA-1||57422^RADON^NICHOLAS^^^^^^NIST-AA-1^L|\rRXA|0|1|20170530||03^MMR^CVX|0.5|mL^milliliters^UCUM||00^Administered^NIP001||||||P3400YX||MSD^Merck and Co^MVX||||A|\rRXR|SC^^HL70162|LA^^HL70163|\rOBX|1|CE|64994-7^Vaccine funding program eligibility category^LN|1|V02^VFC eligible - Medicaid/Medicaid Managed Care^HL70064||||||F|||20170530|||VXC40^Eligibility captured at the immunization level^CDCPHINVS|\rOBX|2|CE|30956-7^Vaccine Type^LN|2|03^MMR^CVX||||||F|\rOBX|3|TS|29768-9^Date vaccine information statement published^LN|2|20120420||||||F|\rOBX|4|TS|29769-7^Date vaccine information statement presented^LN|2|20170530||||||F|","status":"Deprecated","label":"Unknown"},{"typeCode":"PATIENT_ETHNICITY","typeName":"Patient Ethnicity","source":"PID-22","attribute":"","value":"105 E Market St","count":12,"exampleMessage":"MSH|^~\\&|||||20170530103220-0600||VXU^V04^VXU_V04|3SUt-C.01.32.3w|P|2.5.1|\rPID|||3SUt-C.01.32^^^AIRA-TEST^MR||Jernne^Trefusis^Logan^^^^L|Hudspeth^Fantasia|20130531|M||2106-3^White^HL70005|120 Mickel Cir^^Dearborn^MI^48121^USA^P||^PRN^PH^^^313^2395365|||||||||105 E Market St^not Hispanic or Latino^HL70005|\rPD1|||||||||||02^Reminder/Recall - any method^HL70215|||||A|20170530|20170530|\rNK1|1|Orange^Fantasia^^^^^L|MTH^Mother^HL70063|120 Mickel Cir^^Dearborn^MI^48121^USA^P|^PRN^PH^^^313^2395365|\rORC|RE||A07O449.3^AIRA|||||||I-23432^Burden^Donna^A^^^^^NIST-AA-1||57422^RADON^NICHOLAS^^^^^^NIST-AA-1^L|\rRXA|0|1|20170530||03^MMR^CVX|0.5|mL^milliliters^UCUM||00^Administered^NIP001||||||Z7029FR||MSD^Merck and Co^MVX||||A|\rRXR|SC^^HL70162|LA^^HL70163|\rOBX|1|CE|64994-7^Vaccine funding program eligibility category^LN|1|V02^VFC eligible - Medicaid/Medicaid Managed Care^HL70064||||||F|||20170530|||VXC40^Eligibility captured at the immunization level^CDCPHINVS|\rOBX|2|CE|30956-7^Vaccine Type^LN|2|03^MMR^CVX||||||F|\rOBX|3|TS|29768-9^Date vaccine information statement published^LN|2|20120420||||||F|\rOBX|4|TS|29769-7^Date vaccine information statement presented^LN|2|20170530||||||F|","status":"Unrecognized","label":null},{"typeCode":"PATIENT_ETHNICITY","typeName":"Patient Ethnicity","source":"PID-22","attribute":"","value":"KLINGON","count":5,"exampleMessage":"MSH|^~\\&|||||20170530103221-0600||VXU^V04^VXU_V04|3SUt-D.01.108.gg|P|2.5.1|\rPID|||3SUt-D.01.108^^^AIRA-TEST^MR||Sivertsen^Emir^P^^^^L|Ohio^Adelina|20130527|M||2106-3^White^HL70005|193 Henry St^^Milan^MI^48160^USA^P||^PRN^PH^^^734^3967413|||||||||KLINGON^Klingon^CDCREC|\rPD1|||||||||||02^Reminder/Recall - any method^HL70215|||||A|20170530|20170530|\rNK1|1|Dakota^Adelina^^^^^L|MTH^Mother^HL70063|193 Henry St^^Milan^MI^48160^USA^P|^PRN^PH^^^734^3967413|\rORC|RE||L34T750.3^AIRA|||||||I-23432^Burden^Donna^A^^^^^NIST-AA-1||57422^RADON^NICHOLAS^^^^^^NIST-AA-1^L|\rRXA|0|1|20170530||21^Varicella^CVX|0.5|mL^milliliters^UCUM||00^Administered^NIP001||||||G3407KC||MSD^Merck and Co^MVX||||A|\rRXR|SC^^HL70162|LA^^HL70163|\rOBX|1|CE|64994-7^Vaccine funding program eligibility category^LN|1|V03^VFC eligible - Uninsured^HL70064||||||F|||20170530|||VXC40^Eligibility captured at the immunization level^CDCPHINVS|\rOBX|2|CE|30956-7^Vaccine Type^LN|2|21^Varicella^CVX||||||F|\rOBX|3|TS|29768-9^Date vaccine information statement published^LN|2|20080313||||||F|\rOBX|4|TS|29769-7^Date vaccine information statement presented^LN|2|20170530||||||F|","status":"Unrecognized","label":null},{"typeCode":"PATIENT_RACE","typeName":"Patient Race","source":"PID-10","attribute":"","value":"I","count":21,"exampleMessage":"MSH|^~\\&|||||20170530103218-0600||VXU^V04^VXU_V04|3SUt-B.02.08.2jR|P|2.5.1|\rPID|||3SUt-B.02.08^^^AIRA-TEST^MR||Campbell^Szervoc^C^^^^L|Sullivan^Bethshaya|20130604|M||I^American Indian or Alaskan Native^HL70005|85 Carroll St^^Winn^MI^48896^USA^P||^PRN^PH^^^989^2028952|||||||||2186-5^not Hispanic or Latino^HL70005|\rPD1|||||||||||02^Reminder/Recall - any method^HL70215|||||A|20170530|20170530|\rNK1|1|Campbell^Bethshaya^^^^^L|MTH^Mother^HL70063|85 Carroll St^^Winn^MI^48896^USA^P|^PRN^PH^^^989^2028952|\rORC|RE||B92I43.3^AIRA|||||||I-23432^Burden^Donna^A^^^^^NIST-AA-1||57422^RADON^NICHOLAS^^^^^^NIST-AA-1^L|\rRXA|0|1|20170530||21^Varicella^CVX|0.5|mL^milliliters^UCUM||00^Administered^NIP001||||||U6329BP||MSD^Merck and Co^MVX||||A|\rRXR|SC^^HL70162|RA^^HL70163|\rOBX|1|CE|64994-7^Vaccine funding program eligibility category^LN|1|V02^VFC eligible - Medicaid/Medicaid Managed Care^HL70064||||||F|||20170530|||VXC40^Eligibility captured at the immunization level^CDCPHINVS|\rOBX|2|CE|30956-7^Vaccine Type^LN|2|21^Varicella^CVX||||||F|\rOBX|3|TS|29768-9^Date vaccine information statement published^LN|2|20080313||||||F|\rOBX|4|TS|29769-7^Date vaccine information statement presented^LN|2|20170530||||||F|","status":"Deprecated","label":"American Indian or Alaska Native"},{"typeCode":"PATIENT_RACE","typeName":"Patient Race","source":"PID-10","attribute":"","value":"A","count":16,"exampleMessage":"MSH|^~\\&|||||20170530103218-0600||VXU^V04^VXU_V04|3SUt-B.02.09.2jU|P|2.5.1|\rPID|||3SUt-B.02.09^^^AIRA-TEST^MR||Davis^Cleomenes^Giuliana^^^^L|Kent^Elliana|20130525|F||A^Asian or Pacific Islander^HL70005|209 Jackson Ave^^Farmington^MI^48331^USA^P||^PRN^PH^^^248^8867042|||||||||2186-5^not Hispanic or Latino^HL70005|\rPD1|||||||||||02^Reminder/Recall - any method^HL70215|||||A|20170530|20170530|\rNK1|1|Davis^Elliana^^^^^L|MTH^Mother^HL70063|209 Jackson Ave^^Farmington^MI^48331^USA^P|^PRN^PH^^^248^8867042|\rORC|RE||P52I44.3^AIRA|||||||I-23432^Burden^Donna^A^^^^^NIST-AA-1||57422^RADON^NICHOLAS^^^^^^NIST-AA-1^L|\rRXA|0|1|20170530||21^Varicella^CVX|0.5|mL^milliliters^UCUM||00^Administered^NIP001||||||G3407KC||MSD^Merck and Co^MVX||||A|\rRXR|SC^^HL70162|LA^^HL70163|\rOBX|1|CE|64994-7^Vaccine funding program eligibility category^LN|1|V02^VFC eligible - Medicaid/Medicaid Managed Care^HL70064||||||F|||20170530|||VXC40^Eligibility captured at the immunization level^CDCPHINVS|\rOBX|2|CE|30956-7^Vaccine Type^LN|2|21^Varicella^CVX||||||F|\rOBX|3|TS|29768-9^Date vaccine information statement published^LN|2|20080313||||||F|\rOBX|4|TS|29769-7^Date vaccine information statement presented^LN|2|20170530||||||F|","status":"Deprecated","label":"Asian or Pacific Islander"},{"typeCode":"PATIENT_RACE","typeName":"Patient Race","source":"PID-10","attribute":"","value":"B","count":16,"exampleMessage":"MSH|^~\\&|||||20170530103218-0600||VXU^V04^VXU_V04|3SUt-B.02.10.2jX|P|2.5.1|\rPID|||3SUt-B.02.10^^^AIRA-TEST^MR||Baraga^Briac^Aryan^^^^L|Whitaker^Nathalia|20130529|M||B^Black or African-American^HL70005|323 Cherokee St^^Rock^MI^49880^USA^P||^PRN^PH^^^906^2271751|||||||||2186-5^not Hispanic or Latino^HL70005|\rPD1|||||||||||02^Reminder/Recall - any method^HL70215|||||A|20170530|20170530|\rNK1|1|Whitaker^Nathalia^^^^^L|MTH^Mother^HL70063|323 Cherokee St^^Rock^MI^49880^USA^P|^PRN^PH^^^906^2271751|\rORC|RE||I28E45.3^AIRA|||||||I-23432^Burden^Donna^A^^^^^NIST-AA-1||57422^RADON^NICHOLAS^^^^^^NIST-AA-1^L|\rRXA|0|1|20170530||21^Varicella^CVX|0.5|mL^milliliters^UCUM||00^Administered^NIP001||||||U6329BP||MSD^Merck and Co^MVX||||A|\rRXR|SC^^HL70162|RA^^HL70163|\rOBX|1|CE|64994-7^Vaccine funding program eligibility category^LN|1|V02^VFC eligible - Medicaid/Medicaid Managed Care^HL70064||||||F|||20170530|||VXC40^Eligibility captured at the immunization level^CDCPHINVS|\rOBX|2|CE|30956-7^Vaccine Type^LN|2|21^Varicella^CVX||||||F|\rOBX|3|TS|29768-9^Date vaccine information statement published^LN|2|20080313||||||F|\rOBX|4|TS|29769-7^Date vaccine information statement presented^LN|2|20170530||||||F|","status":"Deprecated","label":"Black or African-American"},{"typeCode":"PATIENT_RACE","typeName":"Patient Race","source":"PID-10","attribute":"","value":"W","count":16,"exampleMessage":"MSH|^~\\&|||||20170530103218-0600||VXU^V04^VXU_V04|3SUt-B.02.11.2jZ|P|2.5.1|\rPID|||3SUt-B.02.11^^^AIRA-TEST^MR||Jackson^Tatya^P^^^^L|Winnebago^Mercy|20130603|F||W^White^HL70005|159 Hancock Cir^^Eastport^MI^49627^USA^P||^PRN^PH^^^231^5072822|||||||||2186-5^not Hispanic or Latino^HL70005|\rPD1|||||||||||02^Reminder/Recall - any method^HL70215|||||A|20170530|20170530|\rNK1|1|Jackson^Mercy^^^^^L|MTH^Mother^HL70063|159 Hancock Cir^^Eastport^MI^49627^USA^P|^PRN^PH^^^231^5072822|\rORC|RE||W09S46.3^AIRA|||||||I-23432^Burden^Donna^A^^^^^NIST-AA-1||57422^RADON^NICHOLAS^^^^^^NIST-AA-1^L|\rRXA|0|1|20170530||21^Varicella^CVX|0.5|mL^milliliters^UCUM||00^Administered^NIP001||||||Y5841RR||MSD^Merck and Co^MVX||||A|\rRXR|SC^^HL70162|RA^^HL70163|\rOBX|1|CE|64994-7^Vaccine funding program eligibility category^LN|1|V05^VFC eligible - Federally Qualified Health Center Patient (under-insured)^HL70064||||||F|||20170530|||VXC40^Eligibility captured at the immunization level^CDCPHINVS|\rOBX|2|CE|30956-7^Vaccine Type^LN|2|21^Varicella^CVX||||||F|\rOBX|3|TS|29768-9^Date vaccine information statement published^LN|2|20080313||||||F|\rOBX|4|TS|29769-7^Date vaccine information statement presented^LN|2|20170530||||||F|","status":"Deprecated","label":"White"},{"typeCode":"PATIENT_RACE","typeName":"Patient Race","source":"PID-10","attribute":"","value":"O","count":16,"exampleMessage":"MSH|^~\\&|||||20170530103218-0600||VXU^V04^VXU_V04|3SUt-B.02.12.2k2|P|2.5.1|\rPID|||3SUt-B.02.12^^^AIRA-TEST^MR||Ross^Kadira^M^^^^L|Warren^Ultima|20130519|F||O^Other Race^HL70005|212 John Ave^^Detroit^MI^48201^USA^P||^PRN^PH^^^313^5635014|||||||||2135-2^Hispanic or Latino^HL70005|\rPD1|||||||||||02^Reminder/Recall - any method^HL70215|||||A|20170530|20170530|\rNK1|1|Nolan^Ultima^^^^^L|MTH^Mother^HL70063|212 John Ave^^Detroit^MI^48201^USA^P|^PRN^PH^^^313^5635014|\rORC|RE||D49J47.3^AIRA|||||||I-23432^Burden^Donna^A^^^^^NIST-AA-1||57422^RADON^NICHOLAS^^^^^^NIST-AA-1^L|\rRXA|0|1|20170530||21^Varicella^CVX|0.5|mL^milliliters^UCUM||00^Administered^NIP001||||||U6329BP||MSD^Merck and Co^MVX||||A|\rRXR|SC^^HL70162|RA^^HL70163|\rOBX|1|CE|64994-7^Vaccine funding program eligibility category^LN|1|V04^VFC eligible - American Indian/Alaskan Native^HL70064||||||F|||20170530|||VXC40^Eligibility captured at the immunization level^CDCPHINVS|\rOBX|2|CE|30956-7^Vaccine Type^LN|2|21^Varicella^CVX||||||F|\rOBX|3|TS|29768-9^Date vaccine information statement published^LN|2|20080313||||||F|\rOBX|4|TS|29769-7^Date vaccine information statement presented^LN|2|20170530||||||F|","status":"Deprecated","label":"Other Race"},{"typeCode":"PATIENT_RACE","typeName":"Patient Race","source":"PID-10","attribute":"","value":"U","count":16,"exampleMessage":"MSH|^~\\&|||||20170530103218-0600||VXU^V04^VXU_V04|3SUt-B.02.13.2k8|P|2.5.1|\rPID|||3SUt-B.02.13^^^AIRA-TEST^MR||Lokken^Kali^Bailey^^^^L|Pulaski^Mona|20130526|F||U^Unknown/undetermined^HL70005|199 Haughton Ave^^Kewadin^MI^49648^USA^P||^PRN^PH^^^231^7461399|||||||||2186-5^not Hispanic or Latino^HL70005|\rPD1|||||||||||02^Reminder/Recall - any method^HL70215|||||A|20170530|20170530|\rNK1|1|Armstrong^Mona^^^^^L|MTH^Mother^HL70063|199 Haughton Ave^^Kewadin^MI^49648^USA^P|^PRN^PH^^^231^7461399|\rORC|RE||E51X48.3^AIRA|||||||I-23432^Burden^Donna^A^^^^^NIST-AA-1||57422^RADON^NICHOLAS^^^^^^NIST-AA-1^L|\rRXA|0|1|20170530||21^Varicella^CVX|0.5|mL^milliliters^UCUM||00^Administered^NIP001||||||N3783EO||MSD^Merck and Co^MVX||||A|\rRXR|SC^^HL70162|RA^^HL70163|\rOBX|1|CE|64994-7^Vaccine funding program eligibility category^LN|1|V02^VFC eligible - Medicaid/Medicaid Managed Care^HL70064||||||F|||20170530|||VXC40^Eligibility captured at the immunization level^CDCPHINVS|\rOBX|2|CE|30956-7^Vaccine Type^LN|2|21^Varicella^CVX||||||F|\rOBX|3|TS|29768-9^Date vaccine information statement published^LN|2|20080313||||||F|\rOBX|4|TS|29769-7^Date vaccine information statement presented^LN|2|20170530||||||F|","status":"Deprecated","label":"Unknown"},{"typeCode":"PATIENT_RACE","typeName":"Patient Race","source":"PID-10","attribute":"","value":"1590-9","count":16,"exampleMessage":"MSH|^~\\&|||||20170530103218-0600||VXU^V04^VXU_V04|3SUt-B.03.01.2kb|P|2.5.1|\rPID|||3SUt-B.03.01^^^AIRA-TEST^MR||Grundy^Paris^Pindan^^^^L|Huntingdon^Hayley|20130601|M||1590-9^Ely^HL70005|173 Lyon Ave^^Waterford^MI^48330^USA^P||^PRN^PH^^^248^6663952|||||||||2135-2^Hispanic or Latino^HL70005|\rPD1|||||||||||02^Reminder/Recall - any method^HL70215|||||A|20170530|20170530|\rNK1|1|Grundy^Hayley^^^^^L|MTH^Mother^HL70063|173 Lyon Ave^^Waterford^MI^48330^USA^P|^PRN^PH^^^248^6663952|\rORC|RE||Z18F49.3^AIRA|||||||I-23432^Burden^Donna^A^^^^^NIST-AA-1||57422^RADON^NICHOLAS^^^^^^NIST-AA-1^L|\rRXA|0|1|20170530||94^MMRV^CVX|0.5|mL^milliliters^UCUM||00^Administered^NIP001||||||Q3110HZ||MSD^Merck and Co^MVX||||A|\rRXR|SC^^HL70162|RA^^HL70163|\rOBX|1|CE|64994-7^Vaccine funding program eligibility category^LN|1|V02^VFC eligible - Medicaid/Medicaid Managed Care^HL70064||||||F|||20170530|||VXC40^Eligibility captured at the immunization level^CDCPHINVS|\rOBX|2|CE|30956-7^Vaccine Type^LN|2|94^MMRV^CVX||||||F|\rOBX|3|TS|29768-9^Date vaccine information statement published^LN|2|20100521||||||F|\rOBX|4|TS|29769-7^Date vaccine information statement presented^LN|2|20170530||||||F|","status":"Unrecognized","label":null},{"typeCode":"PATIENT_RACE","typeName":"Patient Race","source":"PID-10","attribute":"","value":"108 N Main St","count":6,"exampleMessage":"MSH|^~\\&|||||20170530103220-0600||VXU^V04^VXU_V04|3SUt-C.02.160.98|P|2.5.1|\rPID|||3SUt-C.02.160^^^AIRA-TEST^MR||Elmore^Christabel^^^^^L|Spiecc^Angela|20130607|F||108 N Main St^Black or African-American^HL70005|239 Poweshiek Cir^^South Rockwood^MI^48179^USA^P||^PRN^PH^^^734^6869151|||||||||2186-5^not Hispanic or Latino^HL70005|\rPD1|||||||||||02^Reminder/Recall - any method^HL70215|||||A|20170530|20170530|\rNK1|1|Elmore^Angela^^^^^L|MTH^Mother^HL70063|239 Poweshiek Cir^^South Rockwood^MI^48179^USA^P|^PRN^PH^^^734^6869151|\rORC|RE||S84T577.3^AIRA|||||||I-23432^Burden^Donna^A^^^^^NIST-AA-1||57422^RADON^NICHOLAS^^^^^^NIST-AA-1^L|\rRXA|0|1|20170530||94^MMRV^CVX|0.5|mL^milliliters^UCUM||00^Administered^NIP001||||||S4121RG||MSD^Merck and Co^MVX||||A|\rRXR|SC^^HL70162|RA^^HL70163|\rOBX|1|CE|64994-7^Vaccine funding program eligibility category^LN|1|V05^VFC eligible - Federally Qualified Health Center Patient (under-insured)^HL70064||||||F|||20170530|||VXC40^Eligibility captured at the immunization level^CDCPHINVS|\rOBX|2|CE|30956-7^Vaccine Type^LN|2|94^MMRV^CVX||||||F|\rOBX|3|TS|29768-9^Date vaccine information statement published^LN|2|20100521||||||F|\rOBX|4|TS|29769-7^Date vaccine information statement presented^LN|2|20170530||||||F|","status":"Unrecognized","label":null},{"typeCode":"PATIENT_RACE","typeName":"Patient Race","source":"PID-10","attribute":"","value":"KLINGON","count":5,"exampleMessage":"MSH|^~\\&|||||20170530103221-0600||VXU^V04^VXU_V04|3SUt-D.01.107.ge|P|2.5.1|\rPID|||3SUt-D.01.107^^^AIRA-TEST^MR||Greenland^Dawn^Fannie^^^^L|Apache^Swati|20130601|F||KLINGON^Klingon^CDCREC|234 Knowles Ave^^Nazareth^MI^49074^USA^P||^PRN^PH^^^269^3551711|||||||||2186-5^not Hispanic or Latino^HL70005|\rPD1|||||||||||02^Reminder/Recall - any method^HL70215|||||A|20170530|20170530|\rNK1|1|Greenland^Swati^^^^^L|MTH^Mother^HL70063|234 Knowles Ave^^Nazareth^MI^49074^USA^P|^PRN^PH^^^269^3551711|\rORC|RE||K55V749.3^AIRA|||||||I-23432^Burden^Donna^A^^^^^NIST-AA-1||57422^RADON^NICHOLAS^^^^^^NIST-AA-1^L|\rRXA|0|1|20170530||21^Varicella^CVX|0.5|mL^milliliters^UCUM||00^Administered^NIP001||||||G3407KC||MSD^Merck and Co^MVX||||A|\rRXR|SC^^HL70162|LA^^HL70163|\rOBX|1|CE|64994-7^Vaccine funding program eligibility category^LN|1|V02^VFC eligible - Medicaid/Medicaid Managed Care^HL70064||||||F|||20170530|||VXC40^Eligibility captured at the immunization level^CDCPHINVS|\rOBX|2|CE|30956-7^Vaccine Type^LN|2|21^Varicella^CVX||||||F|\rOBX|3|TS|29768-9^Date vaccine information statement published^LN|2|20080313||||||F|\rOBX|4|TS|29769-7^Date vaccine information statement presented^LN|2|20170530||||||F|","status":"Unrecognized","label":null},{"typeCode":"PATIENT_GENDER","typeName":"Patient Sex","source":"PID-8","attribute":"","value":"(404)555-3993","count":12,"exampleMessage":"MSH|^~\\&|||||20170530103220-0600||VXU^V04^VXU_V04|3SUt-C.01.34.3A|P|2.5.1|\rPID|||3SUt-C.01.34^^^AIRA-TEST^MR||Hughes^Fulton^T^^^^L|O'Brien^Aliza|20130602|(404)555-3993||2106-3^White^HL70005|268 San Mateo Ln^^Northville Township^MI^48167^USA^P||^PRN^PH^^^248^2272670|||||||||2186-5^not Hispanic or Latino^HL70005|\rPD1|||||||||||02^Reminder/Recall - any method^HL70215|||||A|20170530|20170530|\rNK1|1|Hughes^Aliza^^^^^L|MTH^Mother^HL70063|268 San Mateo Ln^^Northville Township^MI^48167^USA^P|^PRN^PH^^^248^2272670|\rORC|RE||I43R451.3^AIRA|||||||I-23432^Burden^Donna^A^^^^^NIST-AA-1||57422^RADON^NICHOLAS^^^^^^NIST-AA-1^L|\rRXA|0|1|20170530||03^MMR^CVX|0.5|mL^milliliters^UCUM||00^Administered^NIP001||||||V7634SH||MSD^Merck and Co^MVX||||A|\rRXR|SC^^HL70162|LA^^HL70163|\rOBX|1|CE|64994-7^Vaccine funding program eligibility category^LN|1|V02^VFC eligible - Medicaid/Medicaid Managed Care^HL70064||||||F|||20170530|||VXC40^Eligibility captured at the immunization level^CDCPHINVS|\rOBX|2|CE|30956-7^Vaccine Type^LN|2|03^MMR^CVX||||||F|\rOBX|3|TS|29768-9^Date vaccine information statement published^LN|2|20120420||||||F|\rOBX|4|TS|29769-7^Date vaccine information statement presented^LN|2|20170530||||||F|","status":"Unrecognized","label":null},{"typeCode":"PATIENT_PRIMARY_LANGUAGE","typeName":"Person Language","source":"PID-15","attribute":"","value":"(555)555-1123","count":6,"exampleMessage":"MSH|^~\\&|||||20170530103220-0600||VXU^V04^VXU_V04|3SUt-C.02.154.8T|P|2.5.1|\rPID|||3SUt-C.02.154^^^AIRA-TEST^MR||Ellis^Davina^P^^^^L|Wasching^Royale|20130531|F||2106-3^White^HL70005|251 Wilsson Pl^^Reese^MI^48757^USA^P||^PRN^PH^^^989^4200526||(555)555-1123|||||||2186-5^not Hispanic or Latino^HL70005|\rPD1|||||||||||02^Reminder/Recall - any method^HL70215|||||A|20170530|20170530|\rNK1|1|Murray^Royale^^^^^L|MTH^Mother^HL70063|251 Wilsson Pl^^Reese^MI^48757^USA^P|^PRN^PH^^^989^4200526|\rORC|RE||H97Z571.3^AIRA|||||||I-23432^Burden^Donna^A^^^^^NIST-AA-1||57422^RADON^NICHOLAS^^^^^^NIST-AA-1^L|\rRXA|0|1|20170530||94^MMRV^CVX|0.5|mL^milliliters^UCUM||00^Administered^NIP001||||||S4121RG||MSD^Merck and Co^MVX||||A|\rRXR|SC^^HL70162|RA^^HL70163|\rOBX|1|CE|64994-7^Vaccine funding program eligibility category^LN|1|V02^VFC eligible - Medicaid/Medicaid Managed Care^HL70064||||||F|||20170530|||VXC40^Eligibility captured at the immunization level^CDCPHINVS|\rOBX|2|CE|30956-7^Vaccine Type^LN|2|94^MMRV^CVX||||||F|\rOBX|3|TS|29768-9^Date vaccine information statement published^LN|2|20100521||||||F|\rOBX|4|TS|29769-7^Date vaccine information statement presented^LN|2|20170530||||||F|","status":"Unrecognized","label":null},{"typeCode":"PATIENT_NAME_TYPE_CODE","typeName":"Person Name Type","source":"PID-5.7","attribute":"","value":"Samuel","count":12,"exampleMessage":"MSH|^~\\&|||||20170530103220-0600||VXU^V04^VXU_V04|3SUt-C.02.149.8z|P|2.5.1|\rPID|||3SUt-C.02.149^^^AIRA-TEST^MR||Osage^Hilzarie^Rosine^^^^Samuel|Osage^Aegea|20130613|F||2106-3^White^HL70005|372 Saginaw Ave^^Mc Bain^MI^49657^USA^P||^PRN^PH^^^231^5937020|||||||||2186-5^not Hispanic or Latino^HL70005|\rPD1|||||||||||02^Reminder/Recall - any method^HL70215|||||A|20170530|20170530|\rNK1|1|Allen^Aegea^^^^^L|MTH^Mother^HL70063|372 Saginaw Ave^^Mc Bain^MI^49657^USA^P|^PRN^PH^^^231^5937020|\rORC|RE||A72W566.3^AIRA|||||||I-23432^Burden^Donna^A^^^^^NIST-AA-1||57422^RADON^NICHOLAS^^^^^^NIST-AA-1^L|\rRXA|0|1|20170530||03^MMR^CVX|0.5|mL^milliliters^UCUM||00^Administered^NIP001||||||U1747GW||MSD^Merck and Co^MVX||||A|\rRXR|SC^^HL70162|LA^^HL70163|\rOBX|1|CE|64994-7^Vaccine funding program eligibility category^LN|1|V03^VFC eligible - Uninsured^HL70064||||||F|||20170530|||VXC40^Eligibility captured at the immunization level^CDCPHINVS|\rOBX|2|CE|30956-7^Vaccine Type^LN|2|03^MMR^CVX||||||F|\rOBX|3|TS|29768-9^Date vaccine information statement published^LN|2|20120420||||||F|\rOBX|4|TS|29769-7^Date vaccine information statement presented^LN|2|20170530||||||F|","status":"Unrecognized","label":null},{"typeCode":"NEXT_OF_KIN_RELATIONSHIP","typeName":"Person Relationship","source":"NK1-3","attribute":"","value":"BRO","count":16,"exampleMessage":"MSH|^~\\&|||||20170530103219-0600||VXU^V04^VXU_V04|3SUt-B.10.01.2mw|P|2.5.1|\rPID|||3SUt-B.10.01^^^AIRA-TEST^MR||Bolgen^Damodar^Karson^^^^L|Jakobsen^Sile|20130526|M||2106-3^White^HL70005|70 Nelsen Ln^^Long Lake^MI^48743^USA^P||^PRN^PH^^^989^2326485|||||||||2186-5^not Hispanic or Latino^HL70005|\rPD1|||||||||||02^Reminder/Recall - any method^HL70215|||||A|20170530|20170530|\rNK1|1|Jakobsen^Sile^^^^^L|BRO^Brother^HL70063|70 Nelsen Ln^^Long Lake^MI^48743^USA^P|^PRN^PH^^^989^2326485|\rORC|RE||G25Q107.3^AIRA|||||||I-23432^Burden^Donna^A^^^^^NIST-AA-1||57422^RADON^NICHOLAS^^^^^^NIST-AA-1^L|\rRXA|0|1|20170530||21^Varicella^CVX|0.5|mL^milliliters^UCUM||00^Administered^NIP001||||||U6329BP||MSD^Merck and Co^MVX||||A|\rRXR|SC^^HL70162|RA^^HL70163|\rOBX|1|CE|64994-7^Vaccine funding program eligibility category^LN|1|V02^VFC eligible - Medicaid/Medicaid Managed Care^HL70064||||||F|||20170530|||VXC40^Eligibility captured at the immunization level^CDCPHINVS|\rOBX|2|CE|30956-7^Vaccine Type^LN|2|21^Varicella^CVX||||||F|\rOBX|3|TS|29768-9^Date vaccine information statement published^LN|2|20080313||||||F|\rOBX|4|TS|29769-7^Date vaccine information statement presented^LN|2|20170530||||||F|","status":"Ignored","label":"Brother"},{"typeCode":"NEXT_OF_KIN_RELATIONSHIP","typeName":"Person Relationship","source":"NK1-3","attribute":"","value":"OTH","count":16,"exampleMessage":"MSH|^~\\&|||||20170530103219-0600||VXU^V04^VXU_V04|3SUt-B.10.09.2mQ|P|2.5.1|\rPID|||3SUt-B.10.09^^^AIRA-TEST^MR||Colon^Jarmila^Leba^^^^L|Dill^Caitlin|20130526|F||2106-3^White^HL70005|5 Uvalde St^^Daggett^MI^49821^USA^P||^PRN^PH^^^906^9899594|||||||||2186-5^not Hispanic or Latino^HL70005|\rPD1|||||||||||02^Reminder/Recall - any method^HL70215|||||A|20170530|20170530|\rNK1|1|Colon^Caitlin^^^^^L|OTH^Other^HL70063|5 Uvalde St^^Daggett^MI^49821^USA^P|^PRN^PH^^^906^9899594|\rORC|RE||N55G115.3^AIRA|||||||I-23432^Burden^Donna^A^^^^^NIST-AA-1||57422^RADON^NICHOLAS^^^^^^NIST-AA-1^L|\rRXA|0|1|20170530||94^MMRV^CVX|0.5|mL^milliliters^UCUM||00^Administered^NIP001||||||S4121RG||MSD^Merck and Co^MVX||||A|\rRXR|SC^^HL70162|RA^^HL70163|\rOBX|1|CE|64994-7^Vaccine funding program eligibility category^LN|1|V02^VFC eligible - Medicaid/Medicaid Managed Care^HL70064||||||F|||20170530|||VXC40^Eligibility captured at the immunization level^CDCPHINVS|\rOBX|2|CE|30956-7^Vaccine Type^LN|2|94^MMRV^CVX||||||F|\rOBX|3|TS|29768-9^Date vaccine information statement published^LN|2|20100521||||||F|\rOBX|4|TS|29769-7^Date vaccine information statement presented^LN|2|20170530||||||F|","status":"Ignored","label":"Other"},{"typeCode":"NEXT_OF_KIN_RELATIONSHIP","typeName":"Person Relationship","source":"NK1-3","attribute":"","value":"SCH","count":16,"exampleMessage":"MSH|^~\\&|||||20170530103219-0600||VXU^V04^VXU_V04|3SUt-B.10.11.2mV|P|2.5.1|\rPID|||3SUt-B.10.11^^^AIRA-TEST^MR||Painter^Wainwright^Ciceron^^^^L|Ellis^Chloe|20130604|M||2054-5^Black or African-American^HL70005|180 Coal St^^Shelby Township^MI^48317^USA^P||^PRN^PH^^^586^2093963|||||||||2135-2^Hispanic or Latino^HL70005|\rPD1|||||||||||02^Reminder/Recall - any method^HL70215|||||A|20170530|20170530|\rNK1|1|Ellis^Chloe^^^^^L|SCH^Step Child^HL70063|180 Coal St^^Shelby Township^MI^48317^USA^P|^PRN^PH^^^586^2093963|\rORC|RE||F45D117.3^AIRA|||||||I-23432^Burden^Donna^A^^^^^NIST-AA-1||57422^RADON^NICHOLAS^^^^^^NIST-AA-1^L|\rRXA|0|1|20170530||03^MMR^CVX|0.5|mL^milliliters^UCUM||00^Administered^NIP001||||||Z7029FR||MSD^Merck and Co^MVX||||A|\rRXR|SC^^HL70162|LA^^HL70163|\rOBX|1|CE|64994-7^Vaccine funding program eligibility category^LN|1|V04^VFC eligible - American Indian/Alaskan Native^HL70064||||||F|||20170530|||VXC40^Eligibility captured at the immunization level^CDCPHINVS|\rOBX|2|CE|30956-7^Vaccine Type^LN|2|03^MMR^CVX||||||F|\rOBX|3|TS|29768-9^Date vaccine information statement published^LN|2|20120420||||||F|\rOBX|4|TS|29769-7^Date vaccine information statement presented^LN|2|20170530||||||F|","status":"Ignored","label":"Step Child"},{"typeCode":"NEXT_OF_KIN_RELATIONSHIP","typeName":"Person Relationship","source":"NK1-3","attribute":"","value":"SEL","count":16,"exampleMessage":"MSH|^~\\&|||||20170530103219-0600||VXU^V04^VXU_V04|3SUt-B.10.12.2mX|P|2.5.1|\rPID|||3SUt-B.10.12^^^AIRA-TEST^MR||Holmes^Kordelia^Sofia^^^^L|Kittitas^Caley|20130530|F||2106-3^White^HL70005|204 Clallam Cir^^Bedford^MI^49020^USA^P||^PRN^PH^^^269^8224661|||||||||2186-5^not Hispanic or Latino^HL70005|\rPD1|||||||||||02^Reminder/Recall - any method^HL70215|||||A|20170530|20170530|\rNK1|1|Carter^Caley^^^^^L|SEL^Self^HL70063|204 Clallam Cir^^Bedford^MI^49020^USA^P|^PRN^PH^^^269^8224661|\rORC|RE||O17J118.3^AIRA|||||||I-23432^Burden^Donna^A^^^^^NIST-AA-1||57422^RADON^NICHOLAS^^^^^^NIST-AA-1^L|\rRXA|0|1|20170530||94^MMRV^CVX|0.5|mL^milliliters^UCUM||00^Administered^NIP001||||||L6696AE||MSD^Merck and Co^MVX||||A|\rRXR|SC^^HL70162|RA^^HL70163|\rOBX|1|CE|64994-7^Vaccine funding program eligibility category^LN|1|V02^VFC eligible - Medicaid/Medicaid Managed Care^HL70064||||||F|||20170530|||VXC40^Eligibility captured at the immunization level^CDCPHINVS|\rOBX|2|CE|30956-7^Vaccine Type^LN|2|94^MMRV^CVX||||||F|\rOBX|3|TS|29768-9^Date vaccine information statement published^LN|2|20100521||||||F|\rOBX|4|TS|29769-7^Date vaccine information statement presented^LN|2|20170530||||||F|","status":"Ignored","label":"Self"},{"typeCode":"NEXT_OF_KIN_RELATIONSHIP","typeName":"Person Relationship","source":"NK1-3","attribute":"","value":"SIB","count":16,"exampleMessage":"MSH|^~\\&|||||20170530103219-0600||VXU^V04^VXU_V04|3SUt-B.10.13.2n0|P|2.5.1|\rPID|||3SUt-B.10.13^^^AIRA-TEST^MR||Ocario^Stowe^Seaborne^^^^L|Sponland^Phylicia|20130525|M||1002-5^American Indian or Alaska Native^HL70005|121 Yakima Cir^^Saint Helen^MI^48656^USA^P||^PRN^PH^^^989^9217600|||||||||2186-5^not Hispanic or Latino^HL70005|\rPD1|||||||||||02^Reminder/Recall - any method^HL70215|||||A|20170530|20170530|\rNK1|1|Ocario^Phylicia^^^^^L|SIB^Sibling^HL70063|121 Yakima Cir^^Saint Helen^MI^48656^USA^P|^PRN^PH^^^989^9217600|\rORC|RE||O86X119.3^AIRA|||||||I-23432^Burden^Donna^A^^^^^NIST-AA-1||57422^RADON^NICHOLAS^^^^^^NIST-AA-1^L|\rRXA|0|1|20170530||21^Varicella^CVX|0.5|mL^milliliters^UCUM||00^Administered^NIP001||||||Y5841RR||MSD^Merck and Co^MVX||||A|\rRXR|SC^^HL70162|RA^^HL70163|\rOBX|1|CE|64994-7^Vaccine funding program eligibility category^LN|1|V02^VFC eligible - Medicaid/Medicaid Managed Care^HL70064||||||F|||20170530|||VXC40^Eligibility captured at the immunization level^CDCPHINVS|\rOBX|2|CE|30956-7^Vaccine Type^LN|2|21^Varicella^CVX||||||F|\rOBX|3|TS|29768-9^Date vaccine information statement published^LN|2|20080313||||||F|\rOBX|4|TS|29769-7^Date vaccine information statement presented^LN|2|20170530||||||F|","status":"Ignored","label":"Sibling"},{"typeCode":"NEXT_OF_KIN_RELATIONSHIP","typeName":"Person Relationship","source":"NK1-3","attribute":"","value":"SIS","count":16,"exampleMessage":"MSH|^~\\&|||||20170530103219-0600||VXU^V04^VXU_V04|3SUt-B.10.14.2n3|P|2.5.1|\rPID|||3SUt-B.10.14^^^AIRA-TEST^MR||Kay^Muhammad^Pongor^^^^L|Muskogee^Elma|20130601|M||2106-3^White^HL70005|331 Smith Pl^^Eckerman^MI^49790^USA^P||^PRN^PH^^^906^7700510|||||||||2186-5^not Hispanic or Latino^HL70005|\rPD1|||||||||||02^Reminder/Recall - any method^HL70215|||||A|20170530|20170530|\rNK1|1|Kay^Elma^^^^^L|SIS^Sister^HL70063|331 Smith Pl^^Eckerman^MI^49790^USA^P|^PRN^PH^^^906^7700510|\rORC|RE||E31R120.3^AIRA|||||||I-23432^Burden^Donna^A^^^^^NIST-AA-1||57422^RADON^NICHOLAS^^^^^^NIST-AA-1^L|\rRXA|0|1|20170530||03^MMR^CVX|0.5|mL^milliliters^UCUM||00^Administered^NIP001||||||Z7029FR||MSD^Merck and Co^MVX||||A|\rRXR|SC^^HL70162|LA^^HL70163|\rOBX|1|CE|64994-7^Vaccine funding program eligibility category^LN|1|V01^Not VFC eligible^HL70064||||||F|||20170530|||VXC40^Eligibility captured at the immunization level^CDCPHINVS|\rOBX|2|CE|30956-7^Vaccine Type^LN|2|03^MMR^CVX||||||F|\rOBX|3|TS|29768-9^Date vaccine information statement published^LN|2|20120420||||||F|\rOBX|4|TS|29769-7^Date vaccine information statement presented^LN|2|20170530||||||F|","status":"Ignored","label":"Sister"},{"typeCode":"NEXT_OF_KIN_RELATIONSHIP","typeName":"Person Relationship","source":"NK1-3","attribute":"","value":"SPO","count":16,"exampleMessage":"MSH|^~\\&|||||20170530103219-0600||VXU^V04^VXU_V04|3SUt-B.10.15.2n6|P|2.5.1|\rPID|||3SUt-B.10.15^^^AIRA-TEST^MR||Howard^Fayne^Alyssa^^^^L|Anderson^Devyn|20130524|F||2106-3^White^HL70005|144 Carbon St^^Clarkston^MI^48346^USA^P||^PRN^PH^^^248^9598675|||||||||2135-2^Hispanic or Latino^HL70005|\rPD1|||||||||||02^Reminder/Recall - any method^HL70215|||||A|20170530|20170530|\rNK1|1|Bingham^Devyn^^^^^L|SPO^Spouse^HL70063|144 Carbon St^^Clarkston^MI^48346^USA^P|^PRN^PH^^^248^9598675|\rORC|RE||A63Y121.3^AIRA|||||||I-23432^Burden^Donna^A^^^^^NIST-AA-1||57422^RADON^NICHOLAS^^^^^^NIST-AA-1^L|\rRXA|0|1|20170530||21^Varicella^CVX|0.5|mL^milliliters^UCUM||00^Administered^NIP001||||||Y5841RR||MSD^Merck and Co^MVX||||A|\rRXR|SC^^HL70162|RA^^HL70163|\rOBX|1|CE|64994-7^Vaccine funding program eligibility category^LN|1|V02^VFC eligible - Medicaid/Medicaid Managed Care^HL70064||||||F|||20170530|||VXC40^Eligibility captured at the immunization level^CDCPHINVS|\rOBX|2|CE|30956-7^Vaccine Type^LN|2|21^Varicella^CVX||||||F|\rOBX|3|TS|29768-9^Date vaccine information statement published^LN|2|20080313||||||F|\rOBX|4|TS|29769-7^Date vaccine information statement presented^LN|2|20170530||||||F|","status":"Ignored","label":"Spouse"},{"typeCode":"NEXT_OF_KIN_RELATIONSHIP","typeName":"Person Relationship","source":"NK1-3","attribute":"","value":"DS","count":12,"exampleMessage":"MSH|^~\\&|||||20170530103220-0600||VXU^V04^VXU_V04|3SUt-C.02.106.6e|P|2.5.1|\rPID|||3SUt-C.02.106^^^AIRA-TEST^MR||Town^Roseanne^C^^^^L|Durbin^Haliey|20130525|F||2106-3^White^HL70005|240 Hockley St^^Ovid^MI^48866^USA^P||^PRN^PH^^^989^3139248|||||||||2186-5^not Hispanic or Latino^HL70005|\rPD1|||||||||||02^Reminder/Recall - any method^HL70215|||||A|20170530|20170530|\rNK1|1|Hudspeth^Haliey^^^^^L|DS^Dog Sitter^HL70063|240 Hockley St^^Ovid^MI^48866^USA^P|^PRN^PH^^^989^3139248|\rORC|RE||V11O523.3^AIRA|||||||I-23432^Burden^Donna^A^^^^^NIST-AA-1||57422^RADON^NICHOLAS^^^^^^NIST-AA-1^L|\rRXA|0|1|20170530||21^Varicella^CVX|0.5|mL^milliliters^UCUM||00^Administered^NIP001||||||G3407KC||MSD^Merck and Co^MVX||||A|\rRXR|SC^^HL70162|LA^^HL70163|\rOBX|1|CE|64994-7^Vaccine funding program eligibility category^LN|1|V03^VFC eligible - Uninsured^HL70064||||||F|||20170530|||VXC40^Eligibility captured at the immunization level^CDCPHINVS|\rOBX|2|CE|30956-7^Vaccine Type^LN|2|21^Varicella^CVX||||||F|\rOBX|3|TS|29768-9^Date vaccine information statement published^LN|2|20080313||||||F|\rOBX|4|TS|29769-7^Date vaccine information statement presented^LN|2|20170530||||||F|","status":"Unrecognized","label":null},{"typeCode":"PATIENT_PHONE_TEL_EQUIP_CODE","typeName":"Telecommunication Equipment","source":"PID-13.3","attribute":"","value":"Allegany","count":6,"exampleMessage":"MSH|^~\\&|||||20170530103220-0600||VXU^V04^VXU_V04|3SUt-C.02.151.8H|P|2.5.1|\rPID|||3SUt-C.02.151^^^AIRA-TEST^MR||Dawes^Kosmo^T^^^^L|Wardle^Hadria|20130601|M||1002-5^American Indian or Alaska Native^HL70005|29 Garrard Ave^^Ida^MI^48140^USA^P||104 E Market St^^Allegany^^^MI^04599|||||||||2186-5^not Hispanic or Latino^HL70005|\rPD1|||||||||||02^Reminder/Recall - any method^HL70215|||||A|20170530|20170530|\rNK1|1|Dawes^Hadria^^^^^L|MTH^Mother^HL70063|29 Garrard Ave^^Ida^MI^48140^USA^P|^PRN^PH^^^734^8877991|\rORC|RE||W63N568.3^AIRA|||||||I-23432^Burden^Donna^A^^^^^NIST-AA-1||57422^RADON^NICHOLAS^^^^^^NIST-AA-1^L|\rRXA|0|1|20170530||03^MMR^CVX|0.5|mL^milliliters^UCUM||00^Administered^NIP001||||||V7634SH||MSD^Merck and Co^MVX||||A|\rRXR|SC^^HL70162|LA^^HL70163|\rOBX|1|CE|64994-7^Vaccine funding program eligibility category^LN|1|V02^VFC eligible - Medicaid/Medicaid Managed Care^HL70064||||||F|||20170530|||VXC40^Eligibility captured at the immunization level^CDCPHINVS|\rOBX|2|CE|30956-7^Vaccine Type^LN|2|03^MMR^CVX||||||F|\rOBX|3|TS|29768-9^Date vaccine information statement published^LN|2|20120420||||||F|\rOBX|4|TS|29769-7^Date vaccine information statement presented^LN|2|20170530||||||F|","status":"Unrecognized","label":null},{"typeCode":"PATIENT_PHONE_TEL_EQUIP_CODE","typeName":"Telecommunication Equipment","source":"PID-13.3","attribute":"","value":"BAD","count":6,"exampleMessage":"MSH|^~\\&|||||20170530103220-0600||VXU^V04^VXU_V04|3SUt-C.02.152.8L|P|2.5.1|\rPID|||3SUt-C.02.152^^^AIRA-TEST^MR||Defiance^Braeden^A^^^^L|Ferry^Ciara|20130612|M||2106-3^White^HL70005|390 Lincoln Cir^^Livonia^MI^48152^USA^P||(734)6979753^PRN^BAD^^^734^6979753|||||||||2186-5^not Hispanic or Latino^HL70005|\rPD1|||||||||||02^Reminder/Recall - any method^HL70215|||||A|20170530|20170530|\rNK1|1|Defiance^Ciara^^^^^L|MTH^Mother^HL70063|390 Lincoln Cir^^Livonia^MI^48152^USA^P|^PRN^PH^^^734^6979753|\rORC|RE||E04S569.3^AIRA|||||||I-23432^Burden^Donna^A^^^^^NIST-AA-1||57422^RADON^NICHOLAS^^^^^^NIST-AA-1^L|\rRXA|0|1|20170530||03^MMR^CVX|0.5|mL^milliliters^UCUM||00^Administered^NIP001||||||V7634SH||MSD^Merck and Co^MVX||||A|\rRXR|SC^^HL70162|LA^^HL70163|\rOBX|1|CE|64994-7^Vaccine funding program eligibility category^LN|1|V02^VFC eligible - Medicaid/Medicaid Managed Care^HL70064||||||F|||20170530|||VXC40^Eligibility captured at the immunization level^CDCPHINVS|\rOBX|2|CE|30956-7^Vaccine Type^LN|2|03^MMR^CVX||||||F|\rOBX|3|TS|29768-9^Date vaccine information statement published^LN|2|20120420||||||F|\rOBX|4|TS|29769-7^Date vaccine information statement presented^LN|2|20170530||||||F|","status":"Unrecognized","label":null},{"typeCode":"PATIENT_PHONE_TEL_USE_CODE","typeName":"Telecommunication Use","source":"PID-13.2","attribute":"","value":"Apt B","count":6,"exampleMessage":"MSH|^~\\&|||||20170530103220-0600||VXU^V04^VXU_V04|3SUt-C.02.153.8O|P|2.5.1|\rPID|||3SUt-C.02.153^^^AIRA-TEST^MR||Lancaster^Derwent^Reading^^^^L|Marlin^Elita|20130529|M||2106-3^White^HL70005|100 Jefferson Pl^^Richmond Township^MI^48062^USA^P||(586)5473364^Apt B^PH^^^586^5473364|||||||||2186-5^not Hispanic or Latino^HL70005|\rPD1|||||||||||02^Reminder/Recall - any method^HL70215|||||A|20170530|20170530|\rNK1|1|Lancaster^Elita^^^^^L|MTH^Mother^HL70063|100 Jefferson Pl^^Richmond Township^MI^48062^USA^P|^PRN^PH^^^586^5473364|\rORC|RE||E64D570.3^AIRA|||||||I-23432^Burden^Donna^A^^^^^NIST-AA-1||57422^RADON^NICHOLAS^^^^^^NIST-AA-1^L|\rRXA|0|1|20170530||94^MMRV^CVX|0.5|mL^milliliters^UCUM||00^Administered^NIP001||||||L6696AE||MSD^Merck and Co^MVX||||A|\rRXR|SC^^HL70162|RA^^HL70163|\rOBX|1|CE|64994-7^Vaccine funding program eligibility category^LN|1|V03^VFC eligible - Uninsured^HL70064||||||F|||20170530|||VXC40^Eligibility captured at the immunization level^CDCPHINVS|\rOBX|2|CE|30956-7^Vaccine Type^LN|2|94^MMRV^CVX||||||F|\rOBX|3|TS|29768-9^Date vaccine information statement published^LN|2|20100521||||||F|\rOBX|4|TS|29769-7^Date vaccine information statement presented^LN|2|20170530||||||F|","status":"Unrecognized","label":null},{"typeCode":"VACCINATION_ACTION_CODE","typeName":"Vaccination Action Code","source":"RXA-21","attribute":"RXA-5.1.1","value":"P","count":6,"exampleMessage":"MSH|^~\\&|||||20170530103220-0600||VXU^V04^VXU_V04|3SUt-C.02.168.9l|P|2.5.1|\rPID|||3SUt-C.02.168^^^AIRA-TEST^MR||Shelby^Rata^A^^^^L|Montour^June|20130519|M||1002-5^American Indian or Alaska Native^HL70005|187 Huron St^^Kentwood^MI^49512^USA^P||^PRN^PH^^^616^8227292|||||||||2186-5^not Hispanic or Latino^HL70005|\rPD1|||||||||||02^Reminder/Recall - any method^HL70215|||||A|20170530|20170530|\rNK1|1|Shelby^June^^^^^L|MTH^Mother^HL70063|187 Huron St^^Kentwood^MI^49512^USA^P|^PRN^PH^^^616^8227292|\rORC|RE||U00O585.3^AIRA|||||||I-23432^Burden^Donna^A^^^^^NIST-AA-1||57422^RADON^NICHOLAS^^^^^^NIST-AA-1^L|\rRXA|0|1|20170530||21^Varicella^CVX|0.5|mL^milliliters^UCUM||00^Administered^NIP001||||||G3407KC||MSD^Merck and Co^MVX||||P|\rRXR|SC^^HL70162|LA^^HL70163|\rOBX|1|CE|64994-7^Vaccine funding program eligibility category^LN|1|V03^VFC eligible - Uninsured^HL70064||||||F|||20170530|||VXC40^Eligibility captured at the immunization level^CDCPHINVS|\rOBX|2|CE|30956-7^Vaccine Type^LN|2|21^Varicella^CVX||||||F|\rOBX|3|TS|29768-9^Date vaccine information statement published^LN|2|20080313||||||F|\rOBX|4|TS|29769-7^Date vaccine information statement presented^LN|2|20170530||||||F|","status":"Unrecognized","label":null},{"typeCode":"VACCINATION_CVX_CODE","typeName":"Vaccination CVX Code","source":"RXA-5","attribute":"00","value":"14000BADVALUE","count":42,"exampleMessage":"MSH|^~\\&|||||20170530103218-0600||VXU^V04^VXU_V04|3SUt-K.01.12.2dF|P|2.5.1|\rPID|||3SUt-K.01.12^^^AIRA-TEST^MR||Jefferson^Dacia^Micki^^^^L|Iowa^Taranga|20130601|F||2106-3^White^HL70005|300 Love Ave^^Detroit^MI^48228^USA^P||^PRN^PH^^^313^4113540|||||||||2186-5^not Hispanic or Latino^HL70005|\rPD1|||||||||||02^Reminder/Recall - any method^HL70215|||||A|20170530|20170530|\rNK1|1|Mackey^Taranga^^^^^L|MTH^Mother^HL70063|300 Love Ave^^Detroit^MI^48228^USA^P|^PRN^PH^^^313^4113540|\rORC|RE||D84Y21.3^AIRA|||||||I-23432^Burden^Donna^A^^^^^NIST-AA-1||57422^RADON^NICHOLAS^^^^^^NIST-AA-1^L|\rRXA|0|1|20170530||14000BADVALUE^Varicella^CVX|0.5|mL^milliliters^UCUM||00^Administered^NIP001||||||U6329BP||MSD^Merck and Co^MVX||||A|\rRXR|SC^^HL70162|RA^^HL70163|\rOBX|1|CE|64994-7^Vaccine funding program eligibility category^LN|1|V01^Not VFC eligible^HL70064||||||F|||20170530|||VXC40^Eligibility captured at the immunization level^CDCPHINVS|\rOBX|2|CE|30956-7^Vaccine Type^LN|2|21^Varicella^CVX||||||F|\rOBX|3|TS|29768-9^Date vaccine information statement published^LN|2|20080313||||||F|\rOBX|4|TS|29769-7^Date vaccine information statement presented^LN|2|20170530||||||F|","status":"Unrecognized","label":null},{"typeCode":"VACCINATION_CVX_CODE","typeName":"Vaccination CVX Code","source":"RXA-5","attribute":"00","value":"PCV","count":24,"exampleMessage":"MSH|^~\\&|||||20170530103220-0600||VXU^V04^VXU_V04|3SUt-C.01.49.47|P|2.5.1|\rPID|||3SUt-C.01.49^^^AIRA-TEST^MR||Berks^Laraine^^^^^L|Canadian^Shubha|20130527|F||2106-3^White^HL70005|106 Miami Pl^^Grand Rapids^MI^49519^USA^P||^PRN^PH^^^616^3801293|||||||||2186-5^not Hispanic or Latino^HL70005|\rPD1|||||||||||02^Reminder/Recall - any method^HL70215|||||A|20170530|20170530|\rNK1|1|Canadian^Shubha^^^^^L|MTH^Mother^HL70063|106 Miami Pl^^Grand Rapids^MI^49519^USA^P|^PRN^PH^^^616^3801293|\rORC|RE||U22W466.3^AIRA|||||||I-23432^Burden^Donna^A^^^^^NIST-AA-1||57422^RADON^NICHOLAS^^^^^^NIST-AA-1^L|\rRXA|0|1|20170530||PCV^MMR^CVX|0.5|mL^milliliters^UCUM||00^Administered^NIP001||||||Z7029FR||MSD^Merck and Co^MVX||||A|\rRXR|SC^^HL70162|LA^^HL70163|\rOBX|1|CE|64994-7^Vaccine funding program eligibility category^LN|1|V02^VFC eligible - Medicaid/Medicaid Managed Care^HL70064||||||F|||20170530|||VXC40^Eligibility captured at the immunization level^CDCPHINVS|\rOBX|2|CE|30956-7^Vaccine Type^LN|2|03^MMR^CVX||||||F|\rOBX|3|TS|29768-9^Date vaccine information statement published^LN|2|20120420||||||F|\rOBX|4|TS|29769-7^Date vaccine information statement presented^LN|2|20170530||||||F|","status":"Unrecognized","label":null},{"typeCode":"VACCINATION_COMPLETION_STATUS","typeName":"Vaccination Completion","source":"RXA-20","attribute":"Administered","value":"MMR","count":12,"exampleMessage":"MSH|^~\\&|||||20170530103220-0600||VXU^V04^VXU_V04|3SUt-C.01.57.4v|P|2.5.1|\rPID|||3SUt-C.01.57^^^AIRA-TEST^MR||Kent^Vega^S^^^^L|Knight^Mariam|20130611|F||2131-1^Other Race^HL70005|314 Smith Pl^^MI Metro^MI^48340^USA^P||^PRN^PH^^^248^3122359|||||||||2186-5^not Hispanic or Latino^HL70005|\rPD1|||||||||||02^Reminder/Recall - any method^HL70215|||||A|20170530|20170530|\rNK1|1|Kent^Mariam^^^^^L|MTH^Mother^HL70063|314 Smith Pl^^MI Metro^MI^48340^USA^P|^PRN^PH^^^248^3122359|\rORC|RE||C30O474.3^AIRA|||||||I-23432^Burden^Donna^A^^^^^NIST-AA-1||57422^RADON^NICHOLAS^^^^^^NIST-AA-1^L|\rRXA|0|1|20170530||03^MMR^CVX|0.5|mL^milliliters^UCUM||00^Administered^NIP001||||||U1747GW||MSD^Merck and Co^MVX|||MMR|A|\rRXR|SC^^HL70162|LA^^HL70163|\rOBX|1|CE|64994-7^Vaccine funding program eligibility category^LN|1|V01^Not VFC eligible^HL70064||||||F|||20170530|||VXC40^Eligibility captured at the immunization level^CDCPHINVS|\rOBX|2|CE|30956-7^Vaccine Type^LN|2|03^MMR^CVX||||||F|\rOBX|3|TS|29768-9^Date vaccine information statement published^LN|2|20120420||||||F|\rOBX|4|TS|29769-7^Date vaccine information statement presented^LN|2|20170530||||||F|","status":"Unrecognized","label":null},{"typeCode":"VACCINATION_INFORMATION_SOURCE","typeName":"Vaccination Information Source","source":"RXA-9","attribute":"RXA-9","value":"LA-SC","count":12,"exampleMessage":"MSH|^~\\&|||||20170530103220-0600||VXU^V04^VXU_V04|3SUt-C.01.64.4K|P|2.5.1|\rPID|||3SUt-C.01.64^^^AIRA-TEST^MR||Brewster^Vera^Adelyn^^^^L|Breckinridge^Sarai|20130604|F||1002-5^American Indian or Alaska Native^HL70005|15 Hunt Pl^^Maple City^MI^49664^USA^P||^PRN^PH^^^231^3318529|||||||||2135-2^Hispanic or Latino^HL70005|\rPD1|||||||||||02^Reminder/Recall - any method^HL70215|||||A|20170530|20170530|\rNK1|1|Frio^Sarai^^^^^L|MTH^Mother^HL70063|15 Hunt Pl^^Maple City^MI^49664^USA^P|^PRN^PH^^^231^3318529|\rORC|RE||Q85N481.3^AIRA|||||||I-23432^Burden^Donna^A^^^^^NIST-AA-1||57422^RADON^NICHOLAS^^^^^^NIST-AA-1^L|\rRXA|0|1|20170530||94^MMRV^CVX|0.5|mL^milliliters^UCUM||LA-SC^Administered^NIP001||||||S4121RG||MSD^Merck and Co^MVX||||A|\rRXR|SC^^HL70162|RA^^HL70163|\rOBX|1|CE|64994-7^Vaccine funding program eligibility category^LN|1|V02^VFC eligible - Medicaid/Medicaid Managed Care^HL70064||||||F|||20170530|||VXC40^Eligibility captured at the immunization level^CDCPHINVS|\rOBX|2|CE|30956-7^Vaccine Type^LN|2|94^MMRV^CVX||||||F|\rOBX|3|TS|29768-9^Date vaccine information statement published^LN|2|20100521||||||F|\rOBX|4|TS|29769-7^Date vaccine information statement presented^LN|2|20170530||||||F|","status":"Unrecognized","label":null},{"typeCode":"VACCINATION_MANUFACTURER_CODE","typeName":"Vaccination Manufacturer Code","source":"RXA-17","attribute":"Administered","value":"Lot #34TTY9","count":6,"exampleMessage":"MSH|^~\\&|||||20170530103220-0600||VXU^V04^VXU_V04|3SUt-C.02.203.at|P|2.5.1|\rPID|||3SUt-C.02.203^^^AIRA-TEST^MR||Marion^Danu^L^^^^L|Branch^Kadence|20130605|F||2106-3^White^HL70005|235 Taylor St^^Burnips^MI^49314^USA^P||^PRN^PH^^^616^7939067|||||||||2186-5^not Hispanic or Latino^HL70005|\rPD1|||||||||||02^Reminder/Recall - any method^HL70215|||||A|20170530|20170530|\rNK1|1|Marion^Kadence^^^^^L|MTH^Mother^HL70063|235 Taylor St^^Burnips^MI^49314^USA^P|^PRN^PH^^^616^7939067|\rORC|RE||R41Z620.3^AIRA|||||||I-23432^Burden^Donna^A^^^^^NIST-AA-1||57422^RADON^NICHOLAS^^^^^^NIST-AA-1^L|\rRXA|0|1|20170530||21^Varicella^CVX|0.5|mL^milliliters^UCUM||00^Administered^NIP001||||||U6329BP||Lot #34TTY9^Merck and Co^MVX||||A|\rRXR|SC^^HL70162|RA^^HL70163|\rOBX|1|CE|64994-7^Vaccine funding program eligibility category^LN|1|V02^VFC eligible - Medicaid/Medicaid Managed Care^HL70064||||||F|||20170530|||VXC40^Eligibility captured at the immunization level^CDCPHINVS|\rOBX|2|CE|30956-7^Vaccine Type^LN|2|21^Varicella^CVX||||||F|\rOBX|3|TS|29768-9^Date vaccine information statement published^LN|2|20080313||||||F|\rOBX|4|TS|29769-7^Date vaccine information statement presented^LN|2|20170530||||||F|","status":"Unrecognized","label":null}]}
